Workbook
Name \0: #REF!
Name \1: #REF!
Name \a: #REF!
Name \AA: '[2]Rate Analysis'!#REF!
Name \b: #N/A
Name \c: #REF!
Name \CC: '[2]Rate Analysis'!#REF!
Name \d: #REF!
Name \d\srh.xls: [3]ANAL!#REF!
Name \E: #REF!
Name \f: #REF!
Name \h: #REF!
Name \i: #REF!
Name \j: #REF!
Name \k: #REF!
Name \L: '[4]Q&pl-V'!#REF!
Name \m: #REF!
Name \n: #REF!
Name \O: #REF!
Name \OO: '[2]Rate Analysis'!#REF!
Name \P: #REF!
Name \q: #REF!
Name \r: #REF!
Name \s: #REF!
Name \t: #REF!
Name \u: #REF!
Name \V: #REF!
Name \w: #REF!
Name \x: #REF!
Name \y: #REF!
Name \z: #REF!
Name _: #REF!
Name ________________________can435: 43.3
Name _______________________can430: 40.73
Name _______________________can435: 43.3
Name ______________________can430: 40.73
Name ______________________can435: 43.3
Name _____________________can430: 40.73
Name _____________________can435: 43.3
Name ____________________can430: 40.73
Name ____________________can435: 43.3
Name ___________________can430: 40.73
Name ___________________can435: 43.3
Name __________________can430: 40.73
Name __________________can435: 43.3
Name _________________can430: 40.73
Name _________________can435: 43.3
Name ________________can430: 40.73
Name ________________can435: 43.3
Name _______________act1: #REF!
Name _______________can430: 40.73
Name _______________can435: 43.3
Name ______________can430: 40.73
Name ______________can435: 43.3
Name ______________exc1: #REF!
Name ______________exc2: #REF!
Name _____________act1: #REF!
Name _____________can430: 40.73
Name _____________can435: 43.3
Name _____________exc1: #REF!

Sheet QUALIFICATION INFORMATION
A1: QUALIFICATION INFORMATION
A2: 1 | B2: FOR INDIVIDUAL BIDDERS | D2: BROADWAY LINKS PRIVATE LIMITED
B3: Address of the Bidder | D3: Registered office at M/s Shakti Earth Movers LLP, C/O-Ajay Kumar, NH 31, Singhol, Sushil Nagar, Begusarai- 851134, BIHAR HEADOFFICE: SRI KRISHNA NAGAR, BEGUSARAI, BIHAR- 851101 EMAIL: broadwaylink@rediffmail.com, Phone: 06243 247984, 242452, 242318, Fax 06243 247984, 246178 Mobile No. 9334136611, 9711055726
A4: 1.1 | B4: COSTITUTIONAL OR LEGAL STATUS OF BIDDER | D4: PRIVATE LIMITED COMPANY (INCORPORATED IN 2001)
B5: [COPY ATTACHED]
B6: PLACE OF REGISTRATION | D6: BIHAR
B7: PRINCIPAL PLACE OF BUSINESS | D7: PATNA BIHAR
B8: POWER OF ATTORNEY OF SIGNATORY OF BID | D8: SANJAY KUMAR SINGH
B9: [ATTACHED] | D9: Power of Attorney attached
A10: 1.2 | B10: TOTAL VALUE OF CIVIL ENGINEERING CONSTRUCTION WORK PERFORMED IN THE LAST FIVE YEARS | F10: FINANCIAL YEAR | H10: TURNOVER Rs. In LAKH | I10: Remarks | J10: MULTIPLYING FACTOR FOR CURRENT FY | K10: ESCALATED VALUE IN Rs. LAKH
B11: [IN RS. LAKH]
F12: 2019-2020 | H12: 19573.254 | I12: AUDITED | J12: 1.2 | K12: =ROUND(H12*J12,6) -> 23487.905
F13: 2020-2021 | H13: 16255.123 | I13: AUDITED | J13: 1.2 | K13: =ROUND(H13*J13,6) -> 19506.148
F14: 2021-2022 | H14: 19459 | I14: AUDITED | J14: 1.15 | K14: =ROUND(H14*J14,6) -> 22377.85
F15: 2022-2023 | H15: 21976 | I15: AUDITED | J15: 1.1 | K15: =ROUND(H15*J15,6) -> 24173.6
F16: 2023-2024 | H16: 22147 | I16: AUDITED | J16: 1.05 | K16: =ROUND(H16*J16,6) -> 23254.35
F17: 2024-25 | H17: 30907.08 | I17: AUDITED | J17: 1 | K17: =ROUND(H17*J17,6) -> 30907.08
F18: TOTAL TURNOVER in Rs. LAKH | H18: =SUM(H13:H17) -> 110744.2 | K18: =SUM(K13:K17) -> 120219.03
F19: AVERAGE TURNOVER IN RS. LAKH | H19: =H18/5 -> 22148.841 | K19: =K18/5 -> 24043.806
A21: 1.3.1 | B21: Work performed as prime contractor, work performed in the past as a nominated subcontractor will also be considered provided the sub-contract involved execution of all main items of work described in the bid document, provided further that all other qualification criteria are satisfied (in the same name) on works of a similar nature over the last five years. **
A22: S.NO. | B22: PROJECT NAME | C22: NAME OF EMPLOYER | D22: DESCRIPTION OF WORK | F22: CONTRACT NO. | G22: VALUE OF CONTRACT (Rs CRORE) | H22: DATE OF ISSUE OF WORK ORDER | I22: STIPULATED PERIOD OF COMPLETION | J22: ACTUAL DATE OF COMPLETION | K22: REMARKS EXPLAINING REASONS FOR DELAY & WORK COMPLETED | L22: BASE YEAR | M22: MULTIPLYING FACTOR | N22: UPDATED VALUE TO 2020-21 PRICE LEVEL (RS CRORE)
A23: 1 | B23: Widening to 2 Lane with paved shoulders & improvement of NH-98 from Km 57.00 to Km 79.147 under NH(O) in the state of Jharkhand (Job No. 098-JHR-2016-17/255) | C23: EE, NH Division, Medininagar | D23: Bituminous Road, GSB, WMM, RCC Drain and RCC Box Culverts, PROTECTION WORKS | F23: 04 SBD/2017-18 dt. 28.04.17 & supplementary agreement vide 03/SBD.2019-20 DT. 4/9/19 | G23: =ROUND(59.6120577+5.4254429,2) -> 65.04 | H23: 28.04.2017 | I23: 18 months | J23: 30.04.2019 | K23: Additional work/ SUPPLEMENTARY AGREEMENT | L23: 2017-18 | M23: 1.2 | N23: =ROUND(G23*M23,4) -> 78.048
A24: 2 | B24: Strengthening and Construction of Black-Top Road on top of Lower Noon left Embankment from 501.00 R.D to 581.00 R.D and Khemait Jheel link Channel left Embankment from 0.00 RD to 35.70 R.D under Flood Control Division Dalsinghsarai. 01SBD/2015-16 | C24: EE, FCD, Dalsinghsarai | D24: Bituminous Road Works, Brick work Retaining Wall | F24: 01-SBD/2015-16 dated 11.04.15 | G24: 46.5796 | H24: 11.04.2015 | I24: 15 months | J24: 31.3.2019 | K24: BLPL SHARE 74% IN BLPL-MGCPL (JV) Construction Completed & Under Maintenance | L24: 2018-19 | M24: 1.2 | N24: =ROUND(G24*M24,4) -> 55.8955
A25: 3 | B25: Construction of Black-Top Road on top of Lower Noon right Embankment from 500.50 R.D 589.00 R.D and Khemait Jheel link right Embankment from 0.00 RD to 33.00 R.D under Flood Control Division Dalsinghsarai | C25: EE, FCD, Dalsinghsarai | D25: Bituminous Road Works, Brick work Retaining Wall | F25: 01/SBD/16-17 dated 17.02.2017 | G25: 54.66 | H25: 17.02.2017 | I25: 15 months | J25: 15.07.2019 | K25: Construction Completed & Under Maintenance | L25: 2016-17 | M25: 1.2 | N25: =ROUND(G25*M25,4) -> 65.592
A26: 4 | B26: RESTORATION AND LINING OF SONE WESTERN LINK CANAL | C26: EE, SONE BARRAGE DIVISION, INDRAPURI | D26: Earth Work, Canal Concrete Lining, Road Works, Pump House, Retaining Wall, Boulder Pitching | F26: 02/SBD/2016-17 DATED 2.2.2017 | G26: =230.08 -> 230.08 | H26: 02.02.2017 | I26: 24 months | J26: 30.04.2022 | K26: BLPL SHARE 27.50% IN BLPL-C&C (JV) SUBCONTRACT 69.70% FROM C&C (LEAD MEMBER) Construction Completed & Under Maintenance | L26: 2016-17 | M26: 1.2 | N26: =ROUND(G26*M26,4) -> 276.096
A27: 5 | B27: CONSTRUCTION OF CANAL AND ITS LINING WORK AND STRUCTURES FROM R.D. 806.40 TO R.D. 827.70 UNDER TIRHUT MAIN CANAL | C27: EE, Tirhut Canal Division, Motipur, Camp- Muzaffarpur | D27: Earth Work, Canal Concrete Lining, Road Works, Pump House, Retaining Wall, Boulder Pitching | F27: 01/SBD/2017-18 DATED 22.11.2017 | G27: =69.4772+48.4676 -> 117.9448 | H27: 01/SBD/2017-18 DATED 22.11.2017 | I27: 18 MONTHS | J27: 31.12.2024 | K27: Work Completed, 31.12.2024 EOT REQUESTED, Final Deviation under progress | L27: 2017-18 | M27: 1.2 | N27: =ROUND(G27*M27,4) -> 141.5338
A28: 6 | B28: Widening and Strengthening of Samastipur-Dalsinghsarai Road in Km. 20.00 to Km. 28.80 (Total Length 7.900 Km.) for the year 2018-19 | C28: EE, RCD, ROSERA | D28: Bituminous & PQC Road works, RCC Drain, Electrical utility shifting works | F28: 01 SBD / 2019-20 DT. 19.07.2019 | G28: 18.906 | H28: 19.07.2019 | I28: 15 MONTHS | J28: 02.12.2020 | L28: 2018-19 | M28: 1.2 | N28: =ROUND(G28*M28,4) -> 22.6872
A29: 7 | B29: Widening & Strengthening of Dharraura Chowk to Mazampur Bajidpur-Bahera Jhanjharpur road in km 0.0 to 11.64 in darbhanga district under Road Division, Benipur for the year 2019-20 | C29: EE, RCD, BENIPUR | D29: Bituminous & PQC Road works, RCC Drain | F29: 18 SBD of 2019-20 DT. 16.03.2020 | G29: 10.5418 | H29: 16.03.2020 | I29: 12 MONTHS | J29: 31.01.2022 | K29: Construction Completed & Under Maintenance | L29: 2019-20 | M29: 1.2 | N29: =ROUND(G29*M29,4) -> 12.6502
A30: 8 | B30: Widening & Strengthening of Supaul to Bauram Road in km 0.00 to 12.20 under Road Division Benipur for the year 2019-20Widening & Strengthening of Supaul to Bauram Road in km 0.00 to 12.20 under Road Division Benipur for the year 2019-20 | C30: EE, RCD, BENIPUR | D30: Bituminous & PQC Road works, RCC BOX CULVERT, RCC Drain | F30: 4 SBD OF 2020-21 Dated 20.07.20 | G30: 32.7 | H30: 20.07.2020 | I30: 19.01.2022 | J30: 15.03.2024 | K30: 18 MONTHS EOT IN PROCESS | L30: 2020-21 | M30: 1.2 | N30: =ROUND(G30*M30,4) -> 39.24
A31: 9 | B31: Widening & Strengthening work of Vishwakarma Chowk to Guabadi,Narayanpipar, Chaurahi Block Head Via-Bakhadda Chowk of Cheriya Bariyarpur Block for the year 2019-20. | C31: EE, RCD, BEGUSARAI | D31: Bituminous & PQC Road works, RCC BOX CULVERT, RCC Drain | F31: 03/2019-20 DT. 04.12.2019 | G31: 25.664388 | H31: 04.12.2019 | I31: 21 MONTHS | J31: 03.12.2021 | K31: COVID-19 | L31: 2019-20 | M31: 1.2 | N31: =ROUND(G31*M31,4) -> 30.7973
A32: 10 | B32: Widening and Strengthening (from Single Lane to Double Lane) of Turki (N.H.-77)-Saraiya (N.H.-102) Road (Km 0.000 to Km 21.825) under PMGSY (RCP-LWE) in the district of Muzaffarpur, Bihar for the year 2019-20 (Package No. BR23RC-119 ) | C32: EE, RCD, RD-1, Muzaffarpur | D32: Bituminous & PQC Road works, RCC BOX CULVERT, RCC Drain | F32: SBD-09 LWE OF 2020-21 | G32: 39.8849 | H32: 11.12.2020 | I32: 10.06.2022 | J32: 31.03.2023 | K32: COVID-19 | L32: 2020-21 | M32: 1.2 | N32: =ROUND(G32*M32,4) -> 47.8619
A33: 11 | B33: Widening and Strenthening of Road from Basariya, NH-28 to Sarairanjan, NH-103 via Ramnagar chowk (Bella-Megh chowk), Jhakhra, Sarairanjan, Saraiya, Morwa under Road Division, Rosera from Ch. Km. 5.600 to 12.270 for the year 2018-19. | C33: EE, RCD, ROSERA | D33: Bituminous & PQC Road works, RCC BOX CULVERT, RCC Drain | F33: 01 (SBD) of 2020-21 dt. 29.05.2020 | G33: 11.025 | H33: 29.05.2020 | J33: 10.03.2022 | K33: 2020-21 | L33: 1.36 | M33: 1.2 | N33: =ROUND(G33*M33,4) -> 13.23
A34: 12 | B34: Widening and Strengthening of Magardahighat to Silout (Durga Asthan) Road in Km 0.00 to 5.00 (Total Length - 5.00 Km) for the year 2019-20. | C34: EE, RCD, Samastipur | D34: Bituminous & PQC Road works, RCC BOX CULVERT, RCC Drain | F34: LOA ISSUED VIDE LETTER NO. 768 DT. 05.09.2020 | G34: 18.280955 | H34: 24.12.2020 | I34: 23.12.2021 | J34: 31.03.2024 EOT 30.04.2024 | K34: 2020-21 | L34: 1.36 | M34: 1.2 | N34: =ROUND(G34*M34,4) -> 21.9371
A35: 13 | B35: WIDENING AND STRENGTHENING OF MUKTAPUR-WARISNAGAR-BHADOGHAT-HATHAURI ROAD IN KM 00 TO 23.300 (TOTAL LENGTH - 23.30 KM) FOR THE YEAR 2019-20 | C35: EE, RCD, Samastipur | D35: Bituminous & PQC Road works, RCC BOX CULVERT, RCC Drain | F35: LOA ISSUED VIDE LETTER NO. 782 DT. 09.09.2020 | G35: 35.066435 | H35: 22.09.2020 | I35: 21.03.2022 | J35: 31.03.2024 EOT 30.04.2024 | K35: 2020-21 | L35: 1.36 | M35: 1.2 | N35: =ROUND(G35*M35,4) -> 42.0797
A36: 14 | B36: Piling, Civil & Structural and Underground Piping Work for new Process units such as NHT, CCR, NAPTHA SPLITTER, BENSAT and MS BLENDING UNITS OF BS-IV PROJECT at Barauni Refinery (Tender No. TP/069107C001/T/BS-IV/16) | C36: IOCL, Refineries Division, New Delhi | D36: Piling, Civil & Structural and Underground Piping Work | F36: FOA Issues vide letter no. TP/068107C001/T/BS-IV/16/FOA/56 dated 28.08.2017 | G36: 80.6892 | H36: 28.08.2017 | I36: 27.02.2019 | J36: 29.06.2020 | K36: Design Engineering Changes, Delay in Site Handover & COVID-19 Order Value 78,66,63,845.75 (without GST) Actual Completion Cost 80,68,92,297.53 (without GST) | L36: 2017-18 | M36: 1.2 | N36: =ROUND(G36*M36,4) -> 96.827
A37: 15 | B37: Civil Works including Building and U.G.Piping Works for HURL Project, Barauni. SUBCONTRACT FROM TECHNIP INDIA LIMITED | C37: Technip India Limited | D37: Civil Earthwork, PCC/RCC Including Buildings and Under Ground Piping | F37: C100006467 dated 07.01.19 Ammend-6 dt. 07.12.2021 | G37: 98.7241 | H37: 07.01.2019 | I37: 31.07.2020 | J37: 31.03.2022 | K37: Works Completed Delay Reasons Covid-19 wave 1 & 2 Completion Cost 987241560.00 (Without GST) | L37: 2018-19 | M37: 1.2 | N37: =ROUND(G37*M37,4) -> 118.4689
A38: 16 | B38: Subcontract for Piling Works of DHDT Unit at IOCL BARAUNI | C38: CB&I India Private Limited (MCDERMOTT) | D38: Piling Works | F38: 356420-SC-03/540493/CO-02 04th August 2021 | G38: 20.047 | H38: 04.08.2021 | J38: 30.01.2023 | K38: Works Completed, Delay in Works due to Increase in Scope | L38: 2021-22 | M38: 1.15 | N38: =ROUND(G38*M38,4) -> 23.0541
A39: 17 | B39: Subcontract for Piling Works for OHCU Project, IOCL Barauni | C39: Technip Energies India Limited, NOIDA | D39: Piling Works | F39: C100008901 DT. 19.06.2021 | G39: 9.8856 | H39: 19.06.2021 | J39: 16.03.2023 | K39: Works Completed, Delay in Works due to Increase in Scope | L39: 2021-22 | M39: 1.15 | N39: =ROUND(G39*M39,4) -> 11.3684
A40: 18 | B40: Subcontract for Piling Work for NHT-ll + ISOM-ll Unit at IOCL, Barauni, Bihar | C40: CB&I India Private Limited (MCDERMOTT) | D40: Piling & Civil Works | F40: 241222-SC-04/560515 Rev-4 12th November 2021 | G40: 14.3451 | H40: 12.11.2021 | J40: 30.08.2023 | K40: Works Completed, Delay in Works due to Increase in Scope | L40: 2021-22 | M40: 1.15 | N40: =ROUND(G40*M40,4) -> 16.4969
A41: 19 | B41: Piling, Civil including Building, Structure, Road and Drainage Works at 100 KLPD ETHANOL Project, BIADA INDUSTRIAL AREA, Begusarai | C41: NEW WAY HOMES PRIVATE LIMITED, New Delhi- 110001 India | D41: Piling, Civil including Buildings, Structure, Road and Drain works | F41: NWHPL-CIVIL-001 N-22030-BOQ1001-2 dt. 20.01.2022 | G41: 38.5666 | H41: 16.03.2022 | J41: 30.09.2023 | L41: 2021-22 | M41: 1.15 | N41: =ROUND(G41*M41,4) -> 44.3516
A43: Certificate (s) from the Engineer (s) in Charge attached | G43: =SUM(G23:G42) -> 968.63148 | N43: =SUM(N23:N42) -> 1158.2156
A45: 1.3.3 | B45: Information on Bid Capacity (Works for which bids have been submitted and works which are yet to be completed) as on the date of this bid.
A46: A | B46: Existing Commitments and on going works:
A47: S.no. | B47: Description of Works | F47: Name of Employer | G47: Place & State | H47: Percentage of participation of Bidder in the project | I47: Contract No./ date of start of project | J47: Value of Works as per Agreement/ LOA in Crore | K47: Value of Works Completed (IN Crore) | L47: Balance Value of Works to be completed in Crore | M47: Anticipated date of Completion | N47: BASE YEAR | O47: MULTIPLYING FACTOR | P47: Balance value of work at 2020-21 Price Level Rs. In Crore | Q47: DATE OF COMP. | R47: COMPLETION % | S47: RA BILL REFERENCE
A48: 1 | B48: 2 | H48: 3 | I48: 4 | J48: 5 | K48: 6 | L48: 7=(5-6) | M48: 8 | P48: 9 (3x7x# updation factor)
A49: 1 | B49: Widening & Strengthening of road from km 38 of Mahnar-Mohiuddinagar-Bachhwara road Mau Bazar to Piparpati-Garhsisai-Bangraha-Barhouna High School-Barhouna Ghat from km 0 to 18.00 (Total length 18.00 km) under Road Division Samastipur | F49: EE, RCD, SAMASTIPUR | G49: SAMASTIPUR, BIHAR | H49: 1 | I49: 03/CMBD/2017-18 dt. 27.07.17 | J49: 15.7853 | K49: 15.6089 | L49: =J49-K49 -> 0.1764 | M49: 26.1.19 CONSTRUCTION WORK COMPLETED | N49: 2017-18 | O49: 1.2 | P49: =ROUND(H49*L49*O49,2) -> 0.21 | R49: =K49/J49 -> 0.98882505 | S49: 17TH RA BILL DATED 10.12.2024
A50: 2 | B50: Lining work of Chausa Branch Canal from Km. 0.000 to Km. 12.924 & restoration of Kochas and Indore distributary under Ganga Pump Canal Division Chousa Buxar | F50: EE, Ganga Pump Canal Division, Chousa Buxar | G50: Chousa, Buxar | H50: 1 | I50: 01SBD/2017-18 dated 04.11.2017 | J50: 86.494 | K50: 79.5716 | L50: =J50-K50 -> 6.9224 | M50: 30.06.2022 EOT REQUESTED TILL 30.06.2025 | N50: 2017-18 | O50: 1.2 | P50: =ROUND(H50*L50*O50,2) -> 8.31 | R50: =K50/J50 -> 0.9199667 | S50: 31ST RA BILL DATED 24.09.2025
A51: 3 | B51: Long Term Output and Performance based Road Maintenance work for the roads Package No.11 A/OPRMC2/ROSERA | F51: EE, RCD, ROSERA | G51: Rosera, Samstipur, Bihar | H51: 1 | I51: 05MBD/2018-19 DT. 20.02.2019 + ADD AGG DT. 04.10.2025 | J51: =101.106+5.2425 -> 106.3485 | K51: 71.6077 | L51: =J51-K51 -> 34.7408 | M51: 21.02.2026 | N51: 2018-19 | O51: 1.2 | P51: =ROUND(H51*L51*O51,2) -> 41.69 | R51: =K51/J51 -> 0.67333061 | S51: 60TH RA BILL DATED 11.12.2025 | U51: =(K51+K52)/(J51+J52) -> 0.75778074
A52: 4 | B52: Long Term Output and Performance based Road Maintenance work for the roads Package No.9A/OPRMC2/Benipur. | F52: EE, BENIPUR, DARBHANGA | G52: BENIPUR, DARBHANGA | H52: 1 | I52: 4/MBD/2018-19 DT. 12.02.2019 + ADD AGG. DT. 17.11.2025 | J52: =107.886+6.4098 -> 114.2958 | K52: 95.5923 | L52: =J52-K52 -> 18.7035 | M52: 11.02.2026 | N52: 2018-19 | O52: 1.2 | P52: =ROUND(H52*L52*O52,2) -> 22.44 | R52: =K52/J52 -> 0.83635882 | S52: 53RD RA BILL DATED 11.11.2025
A53: 5 | B53: Widening and Strengthening (from Single Lane to Double Lane) of Turki (N.H.-77)-Saraiya (N.H.-102) Road (Km 0.000 to Km 21.825) under PMGSY (RCP-LWE) in the district of Muzaffarpur, Bihar for the year 2019-20 (Package No. BR23RC-119 ) | F53: EE, RCD, RD-1, Muzaffarpur | G53: Muzaffarpur, Bihar | H53: 1 | I53: LOA ISSUED VIDE LETTER NO. 2167 DT. 25.11.2020 | J53: 39.8849 | K53: =36.6954+0.3298 -> 37.0252 | L53: =J53-K53 -> 2.8597 | M53: Construction Completed on 31.03.2023 under Maintenance | N53: 2020-21 | O53: 1.2 | P53: =ROUND(H53*L53*O53,2) -> 3.43 | R53: =K53/J53 -> 0.92830119 | S53: Certificate No. 1097 dt. 19.05.2025
A54: 6 | B54: Construction and upgradation of existing Road along Indo-Nepal Border Road Project from Kanhauli to Sursand (Length=49.150 km) Under Sitamarhi District for the year 2019-20 | F54: EE, RCD, SITAMARHI | G54: SITAMARHI, BIHAR | H54: 1 | I54: LOA VIDE LETTER NO. 760 DT.04.06.2021 & Notice to Proceed vide Letter No. 766 dt. 05.06.2021 | J54: 214.65 | K54: 183.5169 | L54: =ROUND(J54-K54,2) -> 31.13 | M54: 30 MONTHS 04.12.2023 | N54: 2021-22 | O54: 1.15 | P54: =ROUND(H54*L54*O54,2) -> 35.8 | R54: =K54/J54 -> 0.85495877 | S54: 19th RA BILL DT. 08.09.2025 | U54: 0 | V54: =U54*K54 -> 0
A55: 7 | B55: Restoration Work of Saran Main Canal From K.m. 0.00 to K.M. 17.00 | F55: EE, SCD, WRD, Gopalganj | G55: Gopalganj, Bihar | H55: 1 | I55: 01-SBD/2023-24 dt. 15.03.2024 & SA 01-SBD/2023-24 dt. 22.10.2024 | J55: 376.37 | K55: 259.9905 | L55: =ROUND(J55-K55,2) -> 116.38 | M55: 15 MONTHS EOT APPROVED TILL 14.06.2026 | N55: 2023-24 | O55: 1.05 | P55: =ROUND(H55*L55*O55,2) -> 122.2 | R55: =K55/J55 -> 0.69078433 | S55: 16TH RA BILL DATED 25.12.2025
J56: =SUM(J49:J55) -> 953.8285 | K56: =SUM(K49:K55) -> 742.9131 | L56: =SUM(L49:L55) -> 210.9128 | O56: VALUE OF B | P56: =SUM(P49:P55) -> 234.08
A57: 8 | B57: Barricading Works for OHCU Project, IOCL Barauni SUBCONTRACT FROM TECHNIP INDIA LIMITED | F57: Technip India Limited | G57: Barauni, Bihar | H57: 1 | I57: TECHNIP/CONS/201744C001/LOI/002 DT. 24.02.2021 SUB-CON APPROVAL DT. 10.04.21 FORM III DT. 25.05.21 | J57: =0.8 -> 0.8 | K57: 0.3912 | L57: =ROUND(J57-K57,2) -> 0.41 | M57: 3 MONTHS 24.08.21 | N57: 2020-21 | O57: 1.2 | R57: =K57/J57 -> 0.489 | S57: 3RD RA BILL FOR WORK DONE TILL 31.01.2022
A58: 9 | B58: Dismantling Works for OHCU Project, IOCL Barauni SUBCONTRACT FROM TECHNIP INDIA LIMITED | F58: Technip India Limited | G58: Barauni, Bihar | H58: 1 | I58: TECHNIP/CONS/201744C001/LOI/004 DT. 09.03.2021 SUB-CON APPROVAL DT. 10.04.21 FORM III DT. 25.03.21 | J58: 2.635 | K58: 1.4475 | L58: =ROUND(J58-K58,2) -> 1.19 | M58: 3 MONTHS 24.08.21 | N58: 2020-21 | O58: 1.2 | R58: =K58/J58 -> 0.54933586 | S58: 7TH RA BILL FOR WORK DONE TILL 30.11.2025
A59: 10 | B59: Civil, UG & Structural Steel Works for OHCU Project, IOCL Barauni SUBCONTRACT FROM TECHNIP INDIA LIMITED | F59: Technip India Limited | G59: Barauni, Bihar | H59: 1 | I59: TECHNIP/CONS/201744C001/LOI/004 DT. 27.04.2021 EFF. DATE OF START 01.06.2021 & ammend 5 dt. 07.03.2024 | J59: 63.7822 | K59: 63.6849 | L59: =ROUND(J59-K59,2) -> 0.1 | M59: 31.03.2023 Anticipated Completion by 31.03.2025 | N59: 2021-22 | O59: 1.15 | P59: =ROUND(H59*L59*O59,2) -> 0.12 | R59: =K59/J59 -> 0.9984745 | S59: 48TH RA BILL FOR WORK DONE TILL 31.07.2025 | U59: =(K59+K58+K57)/(J59+J58+J57) -> 0.97480407
A60: 11 | B60: CONSTRUCTION OF ROADS, STORM WATER DRAINS, CULVERTS, ELECTRICAL & INSTRUMENTATION CABLE TRENCHES, DUCT BANKS ETC. ALONG WITH THE ASSOCIATED JOBS IN OFF-SITE AREAS AS PART OF THE CAPACITY EXPANSION (TO 9.00 MMTPA) PROJECT OF BARAUNI REFINERY OF INDIAN OIL CORPORATION LIMITED AT BARAUNI, BIHAR. | F60: INDIAN OIL CORPORATION LTD | G60: Barauni, Bihar | H60: 1 | I60: FOA NO. IBCE-6373-C00- PJM-TEN-EPCM-23/2020- 21/FOA/027 DATED 03.06.2021 | J60: 19.01 | K60: 12.6129 | L60: =ROUND(J60-K60,2) -> 6.4 | M60: 13 MONTHS 02.07.2022 PTW EXTENDED TILL 31.03.2025 | N60: 2021-22 | O60: 1.15 | P60: =ROUND(H60*L60*O60,2) -> 7.36 | R60: =K60/J60 -> 0.66348764 | S60: 14TH RA BILL FOR WORK DONE TILL 31.12.2024
A61: 12 | B61: SUBCONTRACT FOR CIVIL UG WORKS ON DIESEL HYDROTREATING UNIT (DHDT) AT IOCL, BARAUNI, BIHAR EPCC-05 | F61: CB&I India Private Limited , Gurgaon, Haryana, 122002 India. | G61: Barauni, Bihar | H61: 1 | I61: 356420-SC-04/555591 dt. 10.11.2021 & Ammend 1 dt. 16.01.2024 | J61: 41.8158 | K61: 39.3151 | L61: =ROUND(J61-K61,2) -> 2.5 | M61: 31.12.2024 Anticipated Completion by 31.03.2025 | N61: 2021-22 | O61: 1.15 | P61: =ROUND(H61*L61*O61,2) -> 2.88 | R61: =K61/J61 -> 0.94019725 | S61: 44th RA BILL FOR WORK DONE TILL 31.10.2025
A62: 13 | B62: Mechanical Works for IOCL Barauni Project, Project No. EN-22-1927 (Hydrogen and Nitrogen Generation Unit at IOCL Barauni Refinery) | F62: Prodair Air Products India Pvt. Ltd., IOCL Barauni Refinery | G62: Barauni, Bihar | H62: 1 | I62: Contract No. 4900120303 dated 18.04.2023 & Ammend 3 dt. 02.01.2025 | J62: 72.4656 | K62: 72.31 | L62: =ROUND(J62-K62,2) -> 0.16 | M62: 31.07.2025 | N62: 2023-24 | O62: 1.05 | P62: =ROUND(H62*L62*O62,2) -> 0.17 | R62: =K62/J62 -> 0.99785277 | S62: 25TH RA BILL FOR WORK DONE TILL 25.08.2025
A63: 14 | B63: Composite Works for Unit and Balance Offsite of New Biturox Plant and Allied Facilities of Barauni Refinery of IOCL | F63: INDIAN OIL CORPORATION LTD | G63: Barauni, Bihar | H63: 1 | I63: Work Order No. 71654304 dt. 04.11.2025 | J63: 79.4247 | K63: 0 | L63: =J63-K63 -> 79.4247 | M63: 09.12.2025 | N63: 2025-26 | O63: 1 | P63: =ROUND(H63*L63*O63,2) -> 79.42
I64: Oil & Gas (Piling, Civil, Structure and UG Piping Works) (B) | J64: =SUM(J57:J63) -> 279.9333 | K64: =SUM(K57:K63) -> 189.7616 | L64: =SUM(L57:L63) -> 90.1847 | P64: =SUM(P57:P63) -> 89.95
A65: Certificate (s) from the Engineer (s) in Charge attached | I65: (A) + (B) | J65: =J64+J56 -> 1233.7618 | K65: =K64+K56 -> 932.6747 | L65: =L64+L56 -> 301.0975 | O65: VALUE OF B | P65: =P64+P56 -> 324.03
A67: B | B67: Works for which Bids already submitted:
A68: S.No. | B68: Description of Works | C68: Place & State | D68: Name & Address of Employer | E68: Estimated Value of Works (Rs Cr) | F68: Stipulated Period of Completion | G68: Date when decision is expected | H68: Remarks if any
A69: 1 | B69: 1 | C69: 2 | D69: 3 | E69: 4 | F69: 5 | G69: 6 | H69: 7
A70: 1 | B70: Modernization of Western Main Canal from 0.000 km to 07.100 km of Western main canal of Sone Canal System under Bihar Water Security and Irrigation Modernization Project (BWSIMP) | C70: DEHRI, BIHAR | D70: CE, IC, DEHRI | E70: 241 | F70: 36 MONTHS | G70: BID SUBMISSION DATE 04.09.2025 VALID FOR 180 DAYS | H70: TECHNICAL BID OPEN
A71: 2 | B71: Modernization of Western Main Canal from 7.100 km to 18.700 km and + Added 2.700 Km Distance to Jainagra Lock of Western main canal of Sone Canal System under Bihar Water Security and Irrigation Modernization Project (BWSIMP) | C71: DEHRI, BIHAR | D71: CE, IC, DEHRI | E71: 277 | F71: 36 MONTHS | G71: BID SUBMISSION DATE 04.09.2025 VALID FOR 180 DAYS | H71: TECHNICAL BID OPEN
A72: 3 | B72: Rehabilitation and Modernization of Western Kosi Main Canal from km. 0.00 to km. 18.29 (India Portion) of Western Kosi Irrigation Scheme under Bihar Water Security and Irrigation Modernization Project (BWSIMP) | C72: MADHUNABI, BIHAR | D72: CE, IC, DARBHANGA | E72: 333 | F72: 24 MONTHS | G72: BID SUBMISSION DATE 04.09.2025 VALID FOR 180 DAYS | H72: TECHNICAL BID OPEN
A73: 4 | B73: Rehabilitation and Modernization of Western Kosi Main Canal from KM 18.29 to KM 26.21 (India Portion) of Western Kosi Irrigation Scheme under Bihar Water Security and Irrigation Modernization Project (BWSIMP) | C73: MADHUBANI, BIHAR | D73: CE, IC DARBHANGA | E73: 122 | F73: 24 MONTHS | G73: BID SUBMISSION DATE 04.09.2025 VALID FOR 180 DAYS | H73: TECHNICAL BID OPEN
A74: 5 | B74: Rehabilitation and Modernization of Western Kosi Main Canal from KM 26.21 to KM 36.18 (India Portion) of Western Kosi Irrigation Scheme under Bihar Water Security and Irrigation Modernization Project | C74: MADHUBANI, BIHAR | D74: CE, IC DARBHANGA | E74: 144.1 | F74: 24 MONTHS | G74: BID SUBMISSION DATE 04.09.2025 VALID FOR 180 DAYS | H74: TECHNICAL BID OPEN
A75: 6 | B75: MISCELLANEOUS CIVIL & STRL. WORKS FOR 387 ACRE AREA FOR PANIPAT REFINERY EXPANSION PROJECT (P25) of M/s Indian Oil Corporation Limited (IOCL), India | C75: PANIPAT, HARYANA | D75: IOCL, PANIPAT | E75: 94.68 | F75: 12 MONTHS | G75: BID SUBMISSION DATE 04.12.2025 VALID FOR 180 DAYS | H75: TECHNICAL BID OPEN
E79: =SUM(E70:E78) -> 1211.78
A80: BID CAPACITY CALCULATION
B82: A= | C82: MAXIMUM VALUE OF WORKSEXECUTED IN ANY ONE YEAR DURING THE LAST FIVE YEAR (UPDATED TO THE CURRENT PRICE LEVEL)
C83: FY 2024-25 | D83: VALUE OF WORK DONE= | J83: Rs. In LAKH | K83: =H17 -> 30907.08
C84: MULTIPLYING FACTOR FOR YEAR 1= | K84: 1
G85: HENCE A= | H85: 30907.08X1.0 | J85: Rs. In LAKH | K85: =ROUND(K83*K84,2) -> 30907.08
B87: B= | C87: VALUE AT CURRENT PRICE LEVEL OF THE EXISTING COMMITMENTS AND ONGOING WORKS TO BE COMPLETED DURING THE NEXT 15 MONTHS/1.25 YEAR
I89: HENCE B= | J89: Rs. In LAKH | K89: =P65*100 -> 32403
B91: N | C91: Number of Years prescribed for the completion of works | J91: years | K91: 1.5
B93: Assessed BID Capacity= | C93: A x N x 2.5 - B | D93: = | E93: =K85 -> 30907.08 | F93: x1.5x2.5 | G93: - | H93: =K89 -> 32403 | I93: = | J93: Rs. In LAKH | K93: =(K85*K91*2.5)-K89 -> 83498.55
K94: =(E79*100) -> 121178
K95: =K93-K94 -> -37679.45

Sheet EPC
A1: S. NO. | B1: NAME OF PROJECT | C1: CATEGORY | D1: MULTIPLYING FACTOR | E1: TOTAL VALUE OF WORK DONE | F1: 2017-18 | G1: 2018-19 | H1: 2019-20 | I1: 2020-21 | J1: 2021-22 | K1: 2022-23 | L1: 2023-24 | M1: 2024-25 | N1: CHITRAKOOT | O1: TOTAL PURNEA | P1: TOTAL ARARIA | Q1: TOTAL SHEOHAR | S1: similar nature for FY2 2024-25 | T1: QUALIFYING VALUE
I2: 1.2 | J2: 1.15 | K2: 1.1 | L2: 1.05 | M2: 1 | N2: =5139700000*10% -> 513970000 | O2: 101800000 | P2: 149800000 | Q2: 95323559
A3: 1 | B3: ='[196]QUALIFICATION INFORMATION'!B23 -> RESTORATION AND LINING OF SONE WESTERN LINK CANAL | C3: 4 | D3: =IF(C3=4,0.75,1) -> 0.75 | E3: =2208485169+161863502+199644323 -> 2569992994 | F3: 431125500 | G3: =601820631+10458103 -> 612278734 | H3: 411363698 | I3: =352104465+51617190 -> 403721655 | J3: =320530556+88529571+113001479 -> 522061606 | K3: =91540319+11258638+86642844 -> 189441801 | L3: 0 | M3: 0 | N3: =IF(E3*D3>$N$2,SUMPRODUCT(I3:M3,$I$2:$M$2)*D3,0) -> 9.6991711e+08 | O3: =IF(SUMPRODUCT(I3:M3,$I$2:$M$2)*D3>$O$2,SUMPRODUCT(I3:M3,$I$2:$M$2)*D3,0) -> 9.6991711e+08 | P3: =IF(SUMPRODUCT(I3:M3,$I$2:$M$2)*D3>$P$2,SUMPRODUCT(I3:M3,$I$2:$M$2)*D3,0) -> 9.6991711e+08 | Q3: =IF(SUMPRODUCT(I3:M3,$I$2:$M$2)*D3>$Q$2,SUMPRODUCT(I3:M3,$I$2:$M$2)*D3,0) -> 9.6991711e+08
A4: 2 | B4: ='[196]QUALIFICATION INFORMATION'!B24 -> CONSTRUCTION OF CANAL AND ITS LINING WORK AND STRUCTURES FROM R.D. 806.40 TO R.D. 827.70 UNDER TIRHUT MAIN CANAL | C4: 4 | D4: =IF(C4=4,0.75,1) -> 0.75 | E4: =694771963+484676426 -> 1179448389 | F4: 21852387 | G4: 168584156 | H4: 103897160 | I4: 69072781 | J4: 82542049 | K4: 67974162 | L4: 147021847 | M4: =899019634-657850311 -> 241169323 | N4: =IF(E4*D4>$N$2,SUMPRODUCT(I4:M4,$I$2:$M$2)*D4,0) -> 4.860934e+08 | O4: =IF(SUMPRODUCT(I4:M4,$I$2:$M$2)*D4>$O$2,SUMPRODUCT(I4:M4,$I$2:$M$2)*D4,0) -> 4.860934e+08 | P4: =IF(SUMPRODUCT(I4:M4,$I$2:$M$2)*D4>$P$2,SUMPRODUCT(I4:M4,$I$2:$M$2)*D4,0) -> 4.860934e+08 | Q4: =IF(SUMPRODUCT(I4:M4,$I$2:$M$2)*D4>$Q$2,SUMPRODUCT(I4:M4,$I$2:$M$2)*D4,0) -> 4.860934e+08
A5: 3 | B5: ='[196]QUALIFICATION INFORMATION'!B25 -> Widening and Strengthening of Samastipur-Dalsinghsarai Road in Km. 20.00 to Km. 28.80 (Total Length 7.900 Km.) for the year 2018-19 | C5: 3 | D5: =IF(C5=4,0.75,1) -> 1 | E5: 182581146 | H5: 33344729 | I5: 148109472 | J5: 1126945 | K5: 0 | L5: 0 | M5: 0 | N5: =IF(E5*D5>$N$2,SUMPRODUCT(I5:M5,$I$2:$M$2)*D5,0) -> 0 | O5: =IF(SUMPRODUCT(I5:M5,$I$2:$M$2)*D5>$O$2,SUMPRODUCT(I5:M5,$I$2:$M$2)*D5,0) -> 1.7902735e+08 | P5: =IF(SUMPRODUCT(I5:M5,$I$2:$M$2)*D5>$P$2,SUMPRODUCT(I5:M5,$I$2:$M$2)*D5,0) -> 1.7902735e+08 | Q5: =IF(SUMPRODUCT(I5:M5,$I$2:$M$2)*D5>$Q$2,SUMPRODUCT(I5:M5,$I$2:$M$2)*D5,0) -> 1.7902735e+08 | S5: =E5*1.2 -> 2.1909738e+08 | T5: =S5*4 -> 8.763895e+08
A6: 4 | B6: ='[196]QUALIFICATION INFORMATION'!B26 -> Widening & Strengthening of Dharraura Chowk to Mazampur Bajidpur-Bahera Jhanjharpur road in km 0.0 to 11.64 in darbhanga district under Road Division, Benipur for the year 2019-20 | C6: 3 | D6: =IF(C6=4,0.75,1) -> 1 | E6: 107649145 | I6: 33509377 | J6: 49746587 | K6: 21997765 | L6: 2395416 | M6: 0 | N6: =IF(E6*D6>$N$2,SUMPRODUCT(I6:M6,$I$2:$M$2)*D6,0) -> 0 | O6: =IF(SUMPRODUCT(I6:M6,$I$2:$M$2)*D6>$O$2,SUMPRODUCT(I6:M6,$I$2:$M$2)*D6,0) -> 1.2413256e+08 | P6: =IF(SUMPRODUCT(I6:M6,$I$2:$M$2)*D6>$P$2,SUMPRODUCT(I6:M6,$I$2:$M$2)*D6,0) -> 0 | Q6: =IF(SUMPRODUCT(I6:M6,$I$2:$M$2)*D6>$Q$2,SUMPRODUCT(I6:M6,$I$2:$M$2)*D6,0) -> 1.2413256e+08 | S6: =E6*1.2 -> 129178974 | T6: =S6*4 -> 516715896
A7: 5 | B7: ='[196]QUALIFICATION INFORMATION'!B27 -> Widening & Strengthening of Supaul to Bauram Road in km 0.00 to 12.20 under Road Division Benipur for the year 2019-20Widening & Strengthening of Supaul to Bauram Road in km 0.00 to 12.20 under Road Division Benipur for the year 2019-20 | C7: 3 | D7: =IF(C7=4,0.75,1) -> 1 | E7: 301574869 | I7: 24192903 | J7: 13981258 | K7: 187315688 | L7: 72192685 | M7: 3892335 | N7: =IF(E7*D7>$N$2,SUMPRODUCT(I7:M7,$I$2:$M$2)*D7,0) -> 0 | O7: =IF(SUMPRODUCT(I7:M7,$I$2:$M$2)*D7>$O$2,SUMPRODUCT(I7:M7,$I$2:$M$2)*D7,0) -> 3.3085184e+08 | P7: =IF(SUMPRODUCT(I7:M7,$I$2:$M$2)*D7>$P$2,SUMPRODUCT(I7:M7,$I$2:$M$2)*D7,0) -> 3.3085184e+08 | Q7: =IF(SUMPRODUCT(I7:M7,$I$2:$M$2)*D7>$Q$2,SUMPRODUCT(I7:M7,$I$2:$M$2)*D7,0) -> 3.3085184e+08 | S7: =E7*1.2 -> 3.6188984e+08 | T7: =S7*4 -> 1.4475594e+09
A8: 6 | B8: ='[196]QUALIFICATION INFORMATION'!B28 -> Widening & Strengthening work of Vishwakarma Chowk to Guabadi,Narayanpipar, Chaurahi Block Head Via-Bakhadda Chowk of Cheriya Bariyarpur Block for the year 2019-20. | C8: 3 | D8: =IF(C8=4,0.75,1) -> 1 | E8: 253638626 | I8: 0 | J8: 0 | K8: 253638626 | L8: 0 | M8: 0 | N8: =IF(E8*D8>$N$2,SUMPRODUCT(I8:M8,$I$2:$M$2)*D8,0) -> 0 | O8: =IF(SUMPRODUCT(I8:M8,$I$2:$M$2)*D8>$O$2,SUMPRODUCT(I8:M8,$I$2:$M$2)*D8,0) -> 2.7900249e+08 | P8: =IF(SUMPRODUCT(I8:M8,$I$2:$M$2)*D8>$P$2,SUMPRODUCT(I8:M8,$I$2:$M$2)*D8,0) -> 2.7900249e+08 | Q8: =IF(SUMPRODUCT(I8:M8,$I$2:$M$2)*D8>$Q$2,SUMPRODUCT(I8:M8,$I$2:$M$2)*D8,0) -> 2.7900249e+08 | S8: =E8*1.1 -> 2.7900249e+08 | T8: =S8*4 -> 1.11601e+09
A9: 7 | B9: ='[196]QUALIFICATION INFORMATION'!B29 -> Widening and Strengthening (from Single Lane to Double Lane) of Turki (N.H.-77)-Saraiya (N.H.-102) Road (Km 0.000 to Km 21.825) under PMGSY (RCP-LWE) in the district of Muzaffarpur, Bihar for the year 2019-20 (Package No. BR23RC-119 ) | C9: 3 | D9: =IF(C9=4,0.75,1) -> 1 | E9: 366954282 | I9: 22500000 | J9: 118461863 | K9: 189725569 | L9: 36266850 | M9: 0 | N9: =IF(E9*D9>$N$2,SUMPRODUCT(I9:M9,$I$2:$M$2)*D9,0) -> 0 | O9: =IF(SUMPRODUCT(I9:M9,$I$2:$M$2)*D9>$O$2,SUMPRODUCT(I9:M9,$I$2:$M$2)*D9,0) -> 4.1000946e+08 | P9: =IF(SUMPRODUCT(I9:M9,$I$2:$M$2)*D9>$P$2,SUMPRODUCT(I9:M9,$I$2:$M$2)*D9,0) -> 4.1000946e+08 | Q9: =IF(SUMPRODUCT(I9:M9,$I$2:$M$2)*D9>$Q$2,SUMPRODUCT(I9:M9,$I$2:$M$2)*D9,0) -> 4.1000946e+08 | S9: =E9*1.2 -> 4.4034514e+08 | T9: =S9*4 -> 1.7613806e+09
A10: 8 | B10: ='[196]QUALIFICATION INFORMATION'!B30 -> Widening and Strenthening of Road from Basariya, NH-28 to Sarairanjan, NH-103 via Ramnagar chowk (Bella-Megh chowk), Jhakhra, Sarairanjan, Saraiya, Morwa under Road Division, Rosera from Ch. Km. 5.600 to 12.270 for the year 2018-19. | C10: 3 | D10: =IF(C10=4,0.75,1) -> 1 | E10: 107517004 | I10: 64344549 | J10: 37064081 | K10: 6108374 | L10: 0 | M10: 0 | N10: =IF(E10*D10>$N$2,SUMPRODUCT(I10:M10,$I$2:$M$2)*D10,0) -> 0 | O10: =IF(SUMPRODUCT(I10:M10,$I$2:$M$2)*D10>$O$2,SUMPRODUCT(I10:M10,$I$2:$M$2)*D10,0) -> 1.2655636e+08 | P10: =IF(SUMPRODUCT(I10:M10,$I$2:$M$2)*D10>$P$2,SUMPRODUCT(I10:M10,$I$2:$M$2)*D10,0) -> 0 | Q10: =IF(SUMPRODUCT(I10:M10,$I$2:$M$2)*D10>$Q$2,SUMPRODUCT(I10:M10,$I$2:$M$2)*D10,0) -> 1.2655636e+08 | S10: =E10*1.2 -> 1.290204e+08 | T10: =S10*4 -> 5.1608162e+08
A11: 9 | B11: ='[196]QUALIFICATION INFORMATION'!B31 -> Widening and Strengthening of Magardahighat to Silout (Durga Asthan) Road in Km 0.00 to 5.00 (Total Length - 5.00 Km) for the year 2019-20. | C11: 3 | D11: =IF(C11=4,0.75,1) -> 1 | E11: 185941862 | I11: 15000000 | J11: 93534627 | K11: 55881999 | L11: 9380195 | M11: 12145041 | N11: =IF(E11*D11>$N$2,SUMPRODUCT(I11:M11,$I$2:$M$2)*D11,0) -> 0 | O11: =IF(SUMPRODUCT(I11:M11,$I$2:$M$2)*D11>$O$2,SUMPRODUCT(I11:M11,$I$2:$M$2)*D11,0) -> 2.0902927e+08 | P11: =IF(SUMPRODUCT(I11:M11,$I$2:$M$2)*D11>$P$2,SUMPRODUCT(I11:M11,$I$2:$M$2)*D11,0) -> 2.0902927e+08 | Q11: =IF(SUMPRODUCT(I11:M11,$I$2:$M$2)*D11>$Q$2,SUMPRODUCT(I11:M11,$I$2:$M$2)*D11,0) -> 2.0902927e+08 | S11: =E11*1.2 -> 2.2313023e+08 | T11: =S11*4 -> 8.9252094e+08
A12: 10 | B12: ='[196]QUALIFICATION INFORMATION'!B32 -> WIDENING AND STRENGTHENING OF MUKTAPUR-WARISNAGAR-BHADOGHAT-HATHAURI ROAD IN KM 00 TO 23.300 (TOTAL LENGTH - 23.30 KM) FOR THE YEAR 2019-20 | C12: 3 | D12: =IF(C12=4,0.75,1) -> 1 | E12: 374358829 | I12: 27902890 | J12: 100648490 | K12: 160720095 | L12: 33686032 | M12: 51401321 | N12: =IF(E12*D12>$N$2,SUMPRODUCT(I12:M12,$I$2:$M$2)*D12,0) -> 0 | O12: =IF(SUMPRODUCT(I12:M12,$I$2:$M$2)*D12>$O$2,SUMPRODUCT(I12:M12,$I$2:$M$2)*D12,0) -> 4.1279299e+08 | P12: =IF(SUMPRODUCT(I12:M12,$I$2:$M$2)*D12>$P$2,SUMPRODUCT(I12:M12,$I$2:$M$2)*D12,0) -> 4.1279299e+08 | Q12: =IF(SUMPRODUCT(I12:M12,$I$2:$M$2)*D12>$Q$2,SUMPRODUCT(I12:M12,$I$2:$M$2)*D12,0) -> 4.1279299e+08 | S12: =E12*1.2 -> 4.4923059e+08 | T12: =S12*4 -> 1.7969224e+09
A13: 11 | B13: ='[196]QUALIFICATION INFORMATION'!B34 -> Piling, Civil & Structural and Underground Piping Work for new Process units such as NHT, CCR, NAPTHA SPLITTER, BENSAT and MS BLENDING UNITS OF BS-IV PROJECT at Barauni Refinery (Tender No. TP/069107C001/T/BS-IV/16) | C13: 4 | D13: =IF(C13=4,0.75,1) -> 0.75 | E13: 8.068923e+08 | I13: 37379375 | J13: 0 | K13: 0 | L13: 0 | M13: 0 | N13: =IF(E13*D13>$N$2,SUMPRODUCT(I13:M13,$I$2:$M$2)*D13,0) -> 33641437 | O13: =IF(SUMPRODUCT(I13:M13,$I$2:$M$2)*D13>$O$2,SUMPRODUCT(I13:M13,$I$2:$M$2)*D13,0) -> 0 | P13: =IF(SUMPRODUCT(I13:M13,$I$2:$M$2)*D13>$P$2,SUMPRODUCT(I13:M13,$I$2:$M$2)*D13,0) -> 0 | Q13: =IF(SUMPRODUCT(I13:M13,$I$2:$M$2)*D13>$Q$2,SUMPRODUCT(I13:M13,$I$2:$M$2)*D13,0) -> 0
A14: 12 | B14: ='[196]QUALIFICATION INFORMATION'!B35 -> Civil Works including Building and U.G.Piping Works for HURL Project, Barauni. SUBCONTRACT FROM TECHNIP INDIA LIMITED | C14: 4 | D14: =IF(C14=4,0.75,1) -> 0.75 | E14: 987241560 | G14: 25444257 | H14: 3.8294474e+08 | I14: 3.304307e+08 | J14: 1.5072373e+08 | K14: 97698131 | L14: 0 | M14: 0 | N14: =IF(E14*D14>$N$2,SUMPRODUCT(I14:M14,$I$2:$M$2)*D14,0) -> 5.0798781e+08 | O14: =IF(SUMPRODUCT(I14:M14,$I$2:$M$2)*D14>$O$2,SUMPRODUCT(I14:M14,$I$2:$M$2)*D14,0) -> 5.0798781e+08 | P14: =IF(SUMPRODUCT(I14:M14,$I$2:$M$2)*D14>$P$2,SUMPRODUCT(I14:M14,$I$2:$M$2)*D14,0) -> 5.0798781e+08 | Q14: =IF(SUMPRODUCT(I14:M14,$I$2:$M$2)*D14>$Q$2,SUMPRODUCT(I14:M14,$I$2:$M$2)*D14,0) -> 5.0798781e+08
A15: 13 | B15: ='[196]QUALIFICATION INFORMATION'!B36 -> Subcontract for Piling Works of DHDT Unit at IOCL BARAUNI | C15: 4 | D15: =IF(C15=4,0.75,1) -> 0.75 | E15: 2.0017711e+08 | I15: 0 | J15: 54891840 | K15: 1.4528527e+08 | L15: 0 | M15: 0 | N15: =IF(E15*D15>$N$2,SUMPRODUCT(I15:M15,$I$2:$M$2)*D15,0) -> 0 | O15: =IF(SUMPRODUCT(I15:M15,$I$2:$M$2)*D15>$O$2,SUMPRODUCT(I15:M15,$I$2:$M$2)*D15,0) -> 1.6720456e+08 | P15: =IF(SUMPRODUCT(I15:M15,$I$2:$M$2)*D15>$P$2,SUMPRODUCT(I15:M15,$I$2:$M$2)*D15,0) -> 1.6720456e+08 | Q15: =IF(SUMPRODUCT(I15:M15,$I$2:$M$2)*D15>$Q$2,SUMPRODUCT(I15:M15,$I$2:$M$2)*D15,0) -> 1.6720456e+08
A16: 14 | B16: ='[196]QUALIFICATION INFORMATION'!B37 -> Subcontract for Piling Work for NHT-ll + ISOM-ll Unit at IOCL, Barauni, Bihar | C16: 4 | D16: =IF(C16=4,0.75,1) -> 0.75 | E16: 1.4338209e+08 | I16: 0 | J16: 29308480 | K16: 72973335 | L16: 41100271 | M16: 0 | N16: =IF(E16*D16>$N$2,SUMPRODUCT(I16:M16,$I$2:$M$2)*D16,0) -> 0 | O16: =IF(SUMPRODUCT(I16:M16,$I$2:$M$2)*D16>$O$2,SUMPRODUCT(I16:M16,$I$2:$M$2)*D16,0) -> 1.1784803e+08 | P16: =IF(SUMPRODUCT(I16:M16,$I$2:$M$2)*D16>$P$2,SUMPRODUCT(I16:M16,$I$2:$M$2)*D16,0) -> 0 | Q16: =IF(SUMPRODUCT(I16:M16,$I$2:$M$2)*D16>$Q$2,SUMPRODUCT(I16:M16,$I$2:$M$2)*D16,0) -> 1.1784803e+08
A17: 15 | B17: Lining work of Chausa Branch Canal from Km. 0.000 to Km. 12.924 & restoration of Kochas and Indore distributary under Ganga Pump Canal Division Chousa Buxar | C17: 4 | D17: =IF(C17=4,0.75,1) -> 0.75 | E17: 856248240 | G17: 92065143 | H17: 121697698 | I17: 63006215 | J17: 159821843 | K17: 117652549 | L17: 182038782 | M17: 157995777 | N17: =IF(E17*D17>$N$2,SUMPRODUCT(I17:M17,$I$2:$M$2)*D17,0) -> 5.5346766e+08 | O17: =IF(SUMPRODUCT(I17:M17,$I$2:$M$2)*D17>$O$2,SUMPRODUCT(I17:M17,$I$2:$M$2)*D17,0) -> 5.5346766e+08 | P17: =IF(SUMPRODUCT(I17:M17,$I$2:$M$2)*D17>$P$2,SUMPRODUCT(I17:M17,$I$2:$M$2)*D17,0) -> 5.5346766e+08 | Q17: =IF(SUMPRODUCT(I17:M17,$I$2:$M$2)*D17>$Q$2,SUMPRODUCT(I17:M17,$I$2:$M$2)*D17,0) -> 5.5346766e+08
A18: 16 | B18: Construction and upgradation of existing Road along Indo-Nepal Border Road Project from Kanhauli to Sursand (Length=49.150 km) Under Sitamarhi District for the year 2019-20 | C18: 3 | D18: =IF(C18=4,0.75,1) -> 1 | E18: 2146470638 | F18: 0 | G18: 0 | H18: 0 | I18: 0 | J18: 104217059 | K18: 339438621 | L18: 496000000 | M18: 771844264 | N18: =IF(E18*D18>$N$2,SUMPRODUCT(I18:M18,$I$2:$M$2)*D18,0) -> 1.7858764e+09 | O18: =IF(SUMPRODUCT(I18:M18,$I$2:$M$2)*D18>$O$2,SUMPRODUCT(I18:M18,$I$2:$M$2)*D18,0) -> 1.7858764e+09 | P18: =IF(SUMPRODUCT(I18:M18,$I$2:$M$2)*D18>$P$2,SUMPRODUCT(I18:M18,$I$2:$M$2)*D18,0) -> 1.7858764e+09 | Q18: =IF(SUMPRODUCT(I18:M18,$I$2:$M$2)*D18>$Q$2,SUMPRODUCT(I18:M18,$I$2:$M$2)*D18,0) -> 1.7858764e+09
A19: 17 | B19: Restoration Work of Saran Main Canal From K.m. 0.00 to K.M. 17.00 | C19: 4 | D19: =IF(C19=4,0.75,1) -> 0.75 | E19: 3763700580 | F19: 0 | G19: 0 | H19: 0 | I19: 0 | J19: 0 | K19: 0 | L19: 0 | M19: 2281988960 | N19: =IF(E19*D19>$N$2,SUMPRODUCT(I19:M19,$I$2:$M$2)*D19,0) -> 1711491720 | O19: =IF(SUMPRODUCT(I19:M19,$I$2:$M$2)*D19>$O$2,SUMPRODUCT(I19:M19,$I$2:$M$2)*D19,0) -> 1711491720 | P19: =IF(SUMPRODUCT(I19:M19,$I$2:$M$2)*D19>$P$2,SUMPRODUCT(I19:M19,$I$2:$M$2)*D19,0) -> 1711491720 | Q19: =IF(SUMPRODUCT(I19:M19,$I$2:$M$2)*D19>$Q$2,SUMPRODUCT(I19:M19,$I$2:$M$2)*D19,0) -> 1711491720
F20: =SUM(F3:F19) -> 452977887 | G20: =SUM(G3:G19) -> 8.9837229e+08 | H20: =SUM(H3:H19) -> 1.053248e+09 | I20: =SUM(I3:I19) -> 1.2391699e+09 | J20: =SUM(J3:J19) -> 1.5181305e+09 | K20: =SUM(K3:K19) -> 1.905852e+09 | L20: =SUM(L3:L19) -> 1.0200821e+09 | M20: =SUM(M3:M19) -> 3520437021 | ... Q20: =SUM(Q3:Q19) -> 8.371289e+09
N21: =N2*10 -> 5139700000 | O21: 15266000 | P21: 2246923500 | Q21: 2859706770
N22: =IF(N20>N21,"OK","FAIL") -> OK | O22: =IF(O20>O21,"OK","FAIL") -> OK | P22: =IF(P20>P21,"OK","FAIL") -> OK | Q22: =IF(Q20>Q21,"OK","FAIL") -> OK

Sheet TECHNICAL
A1: S.No. | B1: Sector | C1: Value (in Cr.) | V1: S.No. | W1: Sector | X1: Value (in Cr.)
A2: 1 | B2: Oil & Gas | C2: ='QUALIFICATION INFORMATION'!G36+'QUALIFICATION INFORMATION'!G38+'QUALIFICATION INFORMATION'!G39+'QUALIFICATION INFORMATION'!G40 -> 124.9669 | V2: 1 | W2: Roads & Highways | X2: =SUM('QUALIFICATION INFORMATION'!G23:G25,'QUALIFICATION INFORMATION'!G28:G35) -> 358.34908
A3: 2 | B3: Fertilizer | C3: ='QUALIFICATION INFORMATION'!G37 -> 98.7241 | V3: 2 | W3: Canal Lining | X3: ='QUALIFICATION INFORMATION'!G26+'QUALIFICATION INFORMATION'!G27 -> 348.0248
A4: 3 | B4: Ethanol Plant | C4: ='QUALIFICATION INFORMATION'!G41 -> 38.5666 | V4: 3 | W4: NHAI, SH, MDR, OR | X4: =15.79+36.05+25.29+11.28+10.65+5.09+10.67+15.73+20.69+30.89+18.95+77.45+26.71+50.5+29.99+15 -> 400.73
A5: 4 | B5: Old Oil & GAS | C5: =14.85+49.05 -> 63.9 | V5: 4 | W5: Irrigation Restoration Earthwork | X5: 26.35
B6: TOTAL | C6: =SUM(C2:C5) -> 326.1576 | X6: =SUM(X2:X5) -> 1133.4539
B19: Work | C19: Order Value in Crores | D19: Executed Value in Crores | E19: Balance Work in Crores | W19: Work | X19: Order Value in Crores | Y19: Executed Value in Crores | Z19: Balance Work in Crores
B20: Oil & Gas Piling, Civil & Str with UG Piping | C20: ='QUALIFICATION INFORMATION'!J64-'QUALIFICATION INFORMATION'!J62 -> 207.4677 | D20: ='QUALIFICATION INFORMATION'!K64-'QUALIFICATION INFORMATION'!K62 -> 117.4516 | E20: =C20-D20 -> 90.0161 | W20: Highway Construction | X20: ='QUALIFICATION INFORMATION'!J49+'QUALIFICATION INFORMATION'!J53+'QUALIFICATION INFORMATION'!J54 -> 270.3202 | Y20: ='QUALIFICATION INFORMATION'!K49+'QUALIFICATION INFORMATION'!K53+'QUALIFICATION INFORMATION'!K54 -> 236.151 | Z20: =X20-Y20 -> 34.1692
B21: Oil & Gas Mechanical Str with AG Piping & Equipment | C21: ='QUALIFICATION INFORMATION'!J62 -> 72.4656 | D21: ='QUALIFICATION INFORMATION'!K62 -> 72.31 | E21: =C21-D21 -> 0.1556 | W21: Road Long Term Maintenance | X21: ='QUALIFICATION INFORMATION'!J51+'QUALIFICATION INFORMATION'!J52 -> 220.6443 | Y21: ='QUALIFICATION INFORMATION'!K51+'QUALIFICATION INFORMATION'!K52 -> 167.2 | Z21: =X21-Y21 -> 53.4443
C22: =SUM(C20:C21) -> 279.9333 | D22: =SUM(D20:D21) -> 189.7616 | E22: =SUM(E20:E21) -> 90.1717 | W22: Canal Const. & Lining | X22: ='QUALIFICATION INFORMATION'!J50+'QUALIFICATION INFORMATION'!J55 -> 462.864 | Y22: ='QUALIFICATION INFORMATION'!K50+'QUALIFICATION INFORMATION'!K55 -> 339.5621 | Z22: =X22-Y22 -> 123.3019
X23: =SUM(X20:X22) -> 953.8285 | Y23: =SUM(Y20:Y22) -> 742.9131 | Z23: =SUM(Z20:Z22) -> 210.9154

Sheet peak qty
A1: Peak Construction Capacity for Oil & Gas
A2: S. No. | B2: Major Item of Work | C2: UOM | D2: Total Qty. in Last 3 Years | E2: Peak Prod. Qty. in a Year | F2: Peak Prod. Qty in a Month | G2: Remarks
A3: 1 | B3: Piling 500mm & 600mm Dia | C3: Rm. | D3: 64500 | E3: 38925 | F3: 6500 | G3: IOCL BR09
A4: 2 | B4: Concreting | C4: Cum. | D4: 61062 | E4: 24000 | F4: 2000 | G4: IOCL BR09+HURL
A5: 3 | B5: Structural Steel Supply, Fabrication, Painting Erection | C5: MT | D5: 4033 | E5: 1800 | F5: 150 | G5: IOCL BR09+HGU
A6: 4 | B6: Static Equipment Erection | C6: MT | D6: 2001 | E6: 2001 | F6: 350 | G6: HGU
A7: 5 | B7: Rotary Equipment Erection | C7: MT | D7: 115 | E7: 115 | F7: 25 | G7: HGU
A8: 6 | B8: Package Equipment & Compressor | C8: MT | D8: 106 | E8: 106 | F8: 106 | G8: HGU
A9: 7 | B9: Steam Methane Reformer Erect. | C9: MT | D9: 1436 | E9: 1436 | F9: 150 | G9: HGU
A10: 8 | B10: Steam Boilers & APH | C10: MT | D10: 254.4 | E10: 254.4 | F10: 45 | G10: HGU
A11: 9 | B11: Pressure Parts & Catalyst Tubes | C11: ID | D11: 1275 | E11: 1275 | F11: 600 | G11: HGU
A12: 9 | B12: Above & Below Ground Piping Fabrication | C12: ID | D12: 232724 | E12: 90100 | F12: 6000 | G12: IOCL BR09 + HGU
A13: 10 | B13: AG & UG Piping Erection | C13: IM | D13: 235764 | E13: 95132 | F13: 6350 | G13: IOCL BR09 + HGU
A14: 11 | B14: Catalyst Loading | C14: MT | D14: 900 | E14: 900 | F14: 450 | G14: HGU
A16: Peak Construction Capacity for Roads, CANALS & Infrastructure works.
A17: S. No. | B17: Major Item of Work | C17: UOM | D17: Total Qty. in Last 5 Years | E17: Peak Production Qty. in a Year | F17: Peak Production Qty in a Month | G17: Remarks
A18: 1 | B18: Earthwork | C18: Cum. | D18: 5655060 | E18: 1851375 | F18: 231421 | G18: Roads & Canals
A19: 2 | B19: Concreting | C19: Cum. | D19: 207121 | E19: 53917 | F19: 6750 | G19: Roads & Canals
A20: 3 | B20: HYSD Bar Supply & Fixing | C20: MT | D20: 5607 | E20: 1656 | F20: 207 | G20: Roads & O&G
A21: 4 | B21: GSB+WMM | C21: Cum. | D21: 445624 | E21: 116969 | F21: 13953 | G21: Roads
A22: 5 | B22: Bituminous works (DBM+BC) | C22: Cum. | D22: 75038 | E22: 22457 | F22: 2807 | G22: Roads
A23: 6 | B23: Protection Works (Boulder Pitching) | C23: Cum. | D23: 19063 | E23: 10568 | F23: 1321 | G23: Roads & Canals
A24: 7 | B24: 25mm thick Mastic Asphalt | C24: Sqm. | D24: 10631 | E24: 9341 | F24: 1168 | G24: Roads
A25: 8 | B25: Road Marking | C25: Sqm. | D25: 12414 | E25: 8330 | F25: 1980 | G25: Roads

Sheet FINANCIAL
A1: Net Worth (Rs. In Lacs)
A2: 2018-19 | B2: 2019-20 | C2: 2020-21 | D2: 2021-22 | E2: 2022-23 | F2: 2023-24 | G2: 2024-25
A3: 3947.68 | B3: 5859.67 | C3: 7814.9 | D3: 9675.5 | E3: 11908.1 | F3: 13911.4 | G3: 17041.9
A18: GROSS TURNOVER (Rs. In Lacs)
A19: 2018-19 | B19: 2019-20 | C19: 2020-21 | D19: 2021-22 | E19: 2022-23 | F19: 2023-24 | G19: 2024-25
A20: 20972.9 | B20: 20581.7 | C20: 17341 | D20: 20210.8 | E20: 22572.8 | F20: 22643.2 | G20: 31260.9

Sheet BLPL QTY 25122025
A1: 1.3.2 Quantities of work executed as prime contractor, work performed in the past as a nominated sub-contractor will also be considered provided the sub-contract involved execution of all main items of work described in the bid document, provided further that all other qualification criteria are satisfied (in the same name and style) in the last five years :**
A2: NAME OF THE CONTRACTOR | D2: BROADWAY LINKS PRIVATE LIMITED
A3: Year | B3: Name of the work | C3: Name of the Employer*
D4: TOTAL CONCRETE WORKS | E4: STEEL | F4: BRICK MASONARY | G4: Plaster | H4: Earth works | I4: SAND FILLING | J4: Brick Soling | K4: GSB | L4: WBM | M4: WMM | N4: GSB+WMM+WBM | O4: BM | P4: SDBC | Q4: DBM | R4: BC | S4: TOTAL Bituminous Work | T4: BACKFILLING WITH GRANULAR MATERIAL | U4: FILTER MEDIA | V4: BOULDER PITCHING | W4: RCC PILING | X4: SHEET PILE/ STR. STEEL | Y4: Mastic Asphalt | Z4: ROAD MARKING | AA4: HUME PIPE | AB4: ELECTRICAL POLE SHIFTING (RS.) | AC4: Remarks* (indicate contract Ref) | AD4: REFERENCE PAGE
A5: 2020-21 | B5: RESTORATION AND LINING OF SONE WESTERN LINK CANAL | C5: EE, SONE BARRAGE DIVISION, INDRAPURI | D5: =15798.085*(27.5%+69.7%) -> 15355.739 | H5: =544833.419*(27.5%+69.7%) -> 529578.08 | I5: =16430.994*(27.5%+69.7%) -> 15970.926 | K5: =24451.325*(27.5%+69.7%) -> 23766.688 | N5: =K5+L5+M5 -> 23766.688 | S5: =O5+P5+Q5+R5 -> 0 | V5: =4953.09*(27.5%+69.7%) -> 4814.4035 | AC5: 02/SBD/2016-17 DATED 2.2.2017 BLPL SHARE 27.5%+69.7% subcontract from Lead Member of JV) | AD5: QTY PAGE 8/70
A6: 2020-21 | B6: CONSTRUCTION OF CANAL AND ITS LINING WORK AND STRUCTURES FROM R.D. 806.40 TO R.D. 827.70 UNDER TIRHUT MAIN CANAL | C6: EE, Tirhut Canal Division, Motipur, Camp- Muzaffarpur | D6: =3788.52+2198.16 -> 5986.68 | H6: 543468 | N6: =K6+L6+M6 -> 0 | S6: =O6+P6+Q6+R6 -> 0 | AC6: 01/SBD/2017-18 DATED 22.11.2017 | AD6: =#REF! -> #REF! | AE6: Page no 104
A7: 2020-21 | B7: Lining work of Chausa Branch Canal from 0.000 Km to 12.924 Km & Restoration of Kochas and Indaur Distributary under Ganga Pump Canal Division, Chausa Buxar | C7: EE, GANGA PUMP CANAL DIVISION, BUXAR | D7: 2915.45 | F7: 178.34 | H7: 49521.59 | N7: =K7+L7+M7 -> 0 | S7: =O7+P7+Q7+R7 -> 0 | AC7: 01/SBD/2017-18 DATED 4.11.2017 | AD7: =#REF! -> #REF! | AE7: Page no 105
A8: 2020-21 | B8: Widening and Strengthening of Samastipur-Dalsinghsarai Road in Km. 20.00 to Km. 28.80 (Total Length 7.900 Km.) for the year 2018-19 | C8: EE, RCD, ROSERA | D8: =2660.875+1064.7+683.0365 -> 4408.6115 | H8: 27506.495 | I8: =148.5 -> 148.5 | J8: =990 -> 990 | K8: 3243.15 | M8: 11110.662 | N8: =K8+L8+M8 -> 14353.812 | Q8: 2731.073 | R8: 1373.934 | S8: =O8+P8+Q8+R8 -> 4105.007 | T8: =15.66 -> 15.66 | AB8: 48597927 | AC8: 01 SBD / 2019-20 DT. 19.07.2019 | AD8: =#REF! -> #REF! | AE8: Page no 106
A9: 2020-21 | B9: Widening and Strenthening of Road from Basariya, NH-28 to Sarairanjan, NH-103 via Ramnagar chowk (Bella-Megh chowk), Jhakhra, Sarairanjan, Saraiya, Morwa under Road Division, Rosera from Ch. Km. 5.600 to 12.270 for the year 2018-19. | C9: EE, RCD, ROSERA | D9: =2293.41+304.15 -> 2597.56 | H9: 13126.96 | K9: 6498.44 | M9: 5635.29 | N9: =K9+L9+M9 -> 12133.73 | S9: =O9+P9+Q9+R9 -> 0 | AC9: 01 (SBD) of 2020-21 dt. 29.05.2020 | AD9: QTY PAGE 14/70 | AE9: Page no 109
A10: 2020-21 | B10: Widening & Strengthening work of Vishwakarma Chowk to Guabadi,Narayanpipar, Chaurahi Block Head Via-Bakhadda Chowk of Cheriya Bariyarpur Block for the year 2019-20. | C10: EE, RCD, BEGUSARAI | D10: =196.85+78.75 -> 275.6 | H10: 84658.8 | K10: 21803.397 | M10: 16364.082 | N10: =K10+L10+M10 -> 38167.479 | Q10: 1740.09 | R10: 0 | S10: =O10+P10+Q10+R10 -> 1740.09 | Y10: 0 | AC10: 03/2019-20 DT. 04.12.2019 | AD10: QTY PAGE 15/70 | AE10: Page no 110
A11: 2020-21 | B11: Long Term Output and Performance based Road Maintenance work for the roads Package No.9A/OPRMC2/Benipur. | C11: EE,RCD BENIPUR, DARBHANGA | D11: =1287.746+5125.203 -> 6412.949 | H11: 8597.76 | J11: 5808.726 | K11: 1994.586 | M11: 158.81 | N11: =K11+L11+M11 -> 2153.396 | R11: 8926.94 | S11: =O11+P11+Q11+R11 -> 8926.94 | Y11: 1289.75 | AC11: 4/MBD/2018-19 DT. 12.02.2019 | AD11: QTY PAGE 24/70 | AE11: Page no 119
A12: 2020-21 | B12: Widening & Strengthening of Dharraura Chowk to Mazampur Bajidpur-Bahera Jhanjharpur road in km 0.0 to 11.64 in darbhanga district under Road Division, Benipur for the year 2019-20 | C12: EE,RCD BENIPUR, DARBHANGA | D12: =2172.153+543.375+213.514 -> 2929.042 | H12: 3353.969 | K12: 1582.175 | M12: 1046.22 | N12: =K12+L12+M12 -> 2628.395 | Q12: 187.5 | R12: 0 | S12: =O12+P12+Q12+R12 -> 187.5 | AC12: 18 SBD of 2019-20 dt. 13.03.2020 | AD12: QTY PAGE 16/70 | AE12: Page no 111
A13: 2020-21 | B13: Widening & Strengthening of Supaul to Bauram Road in Km 0.00 to 12.20 under Road Division Benipur for the year 2019-20 | C13: EE,RCD BENIPUR, DARBHANGA | D13: =1818.25+324.67 -> 2142.92 | H13: 21026.12 | K13: 476.6 | N13: =K13+L13+M13 -> 476.6 | S13: =O13+P13+Q13+R13 -> 0 | AC13: 04SBD/2020-21 dt 20.07.2020 | AD13: QTY PAGE 17&18/70 | AE13: Page no 23
A14: 2020-21 | B14: Widening and Strengthening (from Single Lane to Double Lane) of Turki (N.H.-77)-Saraiya (N.H.-102) Road (Km 0.000 to Km 21.825) under PMGSY (RCP-LWE) in the district of Muzaffarpur, Bihar for the year 2019-20 (Package No. BR23RC-119 ) | C14: EE, RCD, RD-1, Muzaffarpur | K14: 3760.13 | M14: 3084.57 | N14: =K14+L14+M14 -> 6844.7 | S14: =O14+P14+Q14+R14 -> 0 | AC14: SBD-09 LWE OF 2020-21 DT 1112.2020 | AD14: QTY PAGE 19/70 | AE14: Page no 114
A15: 2020-21 | B15: Widening & Strengthening of Magardahi Ghat to Siliut (Durga Asthan) road in Km. 0.00 to 5.00 (Total Length 5.00 Km) for the Year 2019-20 | C15: EE, RCD, SAMASTIPUR | H15: 99971.6 | K15: 2568 | M15: 0 | N15: =K15+L15+M15 -> 2568 | S15: =O15+P15+Q15+R15 -> 0 | AC15: 08/EPC of 2020-21 dt. 24.12.2020 | AD15: QTY PAGE 20/70 | AE15: Page no 115
A16: 2020-21 | B16: Widening & Strengthening of Muktapur-Warisnagar-Bhadohighat-Hatauri Road in Km. 00 to 23.300 (Total Length - 23.30 Km) for the year 2019-20 | C16: EE, RCD, SAMASTIPUR | D16: 274.72 | H16: 8287.5 | K16: 2700.55 | M16: 3645 | N16: =K16+L16+M16 -> 6345.55 | Q16: 0 | R16: 0 | S16: =O16+P16+Q16+R16 -> 0 | AC16: 07/SBD of 2020-21 dt. 22.09.2020 | AD16: QTY PAGE 21/70 | AE16: Page no 116
A17: 2020-21 | B17: Piling, Civil & Structural and Underground Piping Work for new Process units such as NHT, CCR, NAPTHA SPLITTER, BENSAT and MS BLENDING UNITS OF BS-IV PROJECT at Barauni Refinery (Tender No. TP/069107C001/T/BS-IV/16) | C17: IOCL, Refineries Division, New Delhi, baraunirefinery@indianoil.in, anoj.jha@ten.com, navin.chandra@ten.com, 06243240159, 240110, 9873079593 | D17: =86.021+0.375+383.095+37.132+56.266+34.301+30.196 -> 627.386
A18: 2020-21 | B18: Civil Works including Building and U.G.Piping Works for HURL Project, Barauni. SUBCONTRACT FROM TECHNIP INDIA LIMITED | C18: Technip India Limited | D18: 9733.953 | E18: 573 | F18: 1943.138 | H18: 24291.871 | L18: 1430.101 | N18: =K18+L18+M18 -> 1430.101 | S18: =O18+P18+Q18+R18 -> 0 | AC18: C100006467 dated 07.01.19 Ammend-7 dt. 30.05.2023 | AD18: QTY PAGE 54/70
A19: 2020-21 | B19: =CONCATENATE(1,B5,",",2,B6,",",3,B7,",",4,B8,",",5,B9,",",6,B10,",",7,B11,",",8,B12,",",9,B13,",",10,B14,",",11,B15,",",12,B16,",",13,B18) -> 1RESTORATION AND LINING OF SONE WESTERN LINK CANAL,2CONSTRUCTION OF CANAL AND ITS LINING WORK AND STRUCTURES FROM R.D. 806.40 TO R.D. 827.70 UNDER TIRHUT MAIN CANAL,3Lining work of Chausa Branch Canal from 0.000 Km to 12.924 Km & Restoration of Kochas and Indaur Distributary under Ganga Pump Canal Division, Chausa Buxar,4Widening and Strengthening of Samastipur-Dalsinghsarai Road in Km. 20.00 to Km. 28.80 (Total Length 7.900 Km.) for the year 2018-19,5Widening and Strenthening of Road from Basariya, NH-28 to Sarairanjan, NH-103 via Ramnagar chowk (Bella-Megh chowk), Jhakhra, Sarairanjan, Saraiya, Morwa under Road Division, Rosera from Ch. Km. 5.600 to 12.270 for the year 2018-19.,6Widening & Strengthening work of Vishwakarma Chowk to Guabadi,Narayanpipar, Chaurahi Block Head Via-Bakhadda Chowk of Cheriya Bariyarpur Block for the year 2019-20.,7 Long Term Output and Performance based Road Maintenance work for the roads Package No.9A/OPRMC2/Benipur.,8Widening & Strengthening of Dharraura Chowk to Mazampur Bajidpur-Bahera Jhanjharpur road in km 0.0 to 11.64 in darbhanga district under Road Division, Benipur for the year 2019-20,9Widening & Strengthening of Supaul to Bauram Road in Km 0.00 to 12.20 under Road Division Benipur for the year 2019-20,10Widening and Strengthening (from Single Lane to Double Lane) of Turki (N.H.-77)-Saraiya (N.H.-102) Road (Km 0.000 to Km 21.825) under PMGSY (RCP-LWE) in the district of Muzaffarpur, Bihar for the year 2019-20 (Package No. BR23RC-119 ),11Widening & Strengthening of Magardahi Ghat to Siliut (Durga Asthan) road in Km. 0.00 to 5.00 (Total Length 5.00 Km) for the Year 2019-20,12Widening & Strengthening of Muktapur-Warisnagar-Bhadohighat-Hatauri Road in Km. 00 to 23.300 (Total Length - 23.30 Km) for the year 2019-20,13Civil Works including Building and U.G.Piping Works for HURL Project, Barauni. SUBCONTRACT FROM TECHNIP INDIA LIMITED | C19: =CONCATENATE(1,C5,",",2,C6,",",3,C7,",",4,C8,",",5,C9,",",6,C10,",",7,C11,",",8,C12,",",9,C13,",",10,C14,",",11,C15,",",12,C16,",",13,C18) -> 1EE, SONE BARRAGE DIVISION, INDRAPURI,2EE, Tirhut Canal Division, Motipur, Camp- Muzaffarpur,3EE, GANGA PUMP CANAL DIVISION, BUXAR,4EE, RCD, ROSERA,5EE, RCD, ROSERA,6EE, RCD, BEGUSARAI,7EE,RCD BENIPUR, DARBHANGA,8EE,RCD BENIPUR, DARBHANGA,9EE,RCD BENIPUR, DARBHANGA,10EE, RCD, RD-1, Muzaffarpur,11EE, RCD, SAMASTIPUR,12EE, RCD, SAMASTIPUR,13Technip India Limited | D19: =SUM(D5:D18) -> 53660.61 | E19: =SUM(E5:E18) -> 573 | F19: =SUM(F5:F18) -> 2121.478 | G19: =SUM(G5:G18) -> 0 | H19: =SUM(H5:H18) -> 1413388.7 | I19: =SUM(I5:I18) -> 16119.426 | J19: =SUM(J5:J18) -> 6798.726 | K19: =SUM(K5:K18) -> 68393.716 | ... AB19: =SUM(AB5:AB18) -> 48597927 | AC19: =CONCATENATE(AC5,",",AC6,",",AC7,",",AC8,",",AC9,",",AC10,",",AC11,",",AC12,",",AC13,",",AC14,",",AC15,",",AC16,",",AC18) -> 02/SBD/2016-17 DATED 2.2.2017 BLPL SHARE 27.5%+69.7% subcontract from Lead Member of JV),01/SBD/2017-18 DATED 22.11.2017,01/SBD/2017-18 DATED 4.11.2017,01 SBD / 2019-20 DT. 19.07.2019,01 (SBD) of 2020-21 dt. 29.05.2020,03/2019-20 DT. 04.12.2019,4/MBD/2018-19 DT. 12.02.2019,18 SBD of 2019-20 dt. 13.03.2020,04SBD/2020-21 dt 20.07.2020,SBD-09 LWE OF 2020-21 DT 1112.2020,08/EPC of 2020-21 dt. 24.12.2020,07/SBD of 2020-21 dt. 22.09.2020,C100006467 dated 07.01.19 Ammend-7 dt. 30.05.2023
A20: 2021-22 | B20: RESTORATION AND LINING OF SONE WESTERN LINK CANAL | C20: EE, SONE BARRAGE DIVISION, INDRAPURI | D20: =17806.9*(27.5%+69.7%) -> 17308.307 | E20: 1.257 | H20: =259601.868*(27.5%+69.7%) -> 252333.02 | I20: =14632.7289*(27.5%+69.7%) -> 14223.012 | K20: =13778.817*(27.5%+69.7%) -> 13393.01 | N20: =K20+L20+M20 -> 13393.01 | S20: =O20+P20+Q20+R20 -> 0 | V20: =6460.909*(27.5%+69.7%) -> 6280.0035 | AC20: 02/SBD/2016-17 DATED 2.2.2017 BLPL SHARE 27.5%+69.7% subcontract from Lead Member of JV) | AD20: QTY PAGE 8/70
A21: 2021-22 | B21: CONSTRUCTION OF CANAL AND ITS LINING WORK AND STRUCTURES FROM R.D. 806.40 TO R.D. 827.70 UNDER TIRHUT MAIN CANAL | C21: EE, Tirhut Canal Division, Motipur, Camp- Muzaffarpur | D21: 5887 | F21: =138.76*0 -> 0 | H21: 0 | N21: =K21+L21+M21 -> 0 | S21: =O21+P21+Q21+R21 -> 0 | AC21: 01/SBD/2017-18 DATED 22.11.2017 | AD21: QTY PAGE 9/70 | AE21: Page no 104
A22: 2021-22 | B22: Lining work of Chausa Branch Canal from 0.000 Km to 12.924 Km & Restoration of Kochas and Indaur Distributary under Ganga Pump Canal Division, Chausa Buxar | C22: EE, GANGA PUMP CANAL DIVISION, BUXAR | D22: =4923.491+216.487 -> 5139.978 | F22: 2069.946 | H22: 244016.79 | N22: =K22+L22+M22 -> 0 | S22: =O22+P22+Q22+R22 -> 0 | AC22: 01/SBD/2017-18 DATED 4.11.2017 | AD22: QTY PAGE 10/70 | AE22: Page no 105
A23: 2021-22 | B23: Widening and Strenthening of Road from Basariya, NH-28 to Sarairanjan, NH-103 via Ramnagar chowk (Bella-Megh chowk), Jhakhra, Sarairanjan, Saraiya, Morwa under Road Division, Rosera from Ch. Km. 5.600 to 12.270 for the year 2018-19. | C23: EE, RCD, ROSERA | D23: 96.25 | H23: 11819.476 | K23: 83.16 | M23: 938.275 | N23: =K23+L23+M23 -> 1021.435 | Q23: 1454.1175 | R23: 793.155 | S23: =O23+P23+Q23+R23 -> 2247.2725 | AB23: 19512027 | AC23: 01 (SBD) of 2020-21 dt. 29.05.2020 | AD23: QTY PAGE 14/70 | AE23: Page no 109
A24: 2021-22 | B24: Widening & Strengthening work of Vishwakarma Chowk to Guabadi,Narayanpipar, Chaurahi Block Head Via-Bakhadda Chowk of Cheriya Bariyarpur Block for the year 2019-20. | C24: EE, RCD, BEGUSARAI | D24: =323.74+126.495 -> 450.235 | H24: 40606.267 | K24: 589.473 | M24: 3291.438 | N24: =K24+L24+M24 -> 3880.911 | Q24: 2975.64 | R24: 2553.3 | S24: =O24+P24+Q24+R24 -> 5528.94 | Y24: 5857.5 | AB24: 7469967 | AC24: 03/2019-20 DT. 04.12.2019 | AD24: QTY PAGE 15/70 | AE24: Page no 110
A25: 2021-22 | B25: Long Term Output and Performance based Road Maintenance work for the roads Package No.9A/OPRMC2/Benipur. | C25: EE,RCD BENIPUR, DARBHANGA | D25: 274.149 | H25: 0 | J25: 0 | K25: 94.08 | M25: 0 | N25: =K25+L25+M25 -> 94.08 | R25: 5903.175 | S25: =O25+P25+Q25+R25 -> 5903.175 | Y25: 0 | AC25: 4/MBD/2018-19 DT. 12.02.2019 | AD25: QTY PAGE 23/70 | AE25: Page no 118
A26: 2021-22 | B26: Widening & Strengthening of Dharraura Chowk to Mazampur Bajidpur-Bahera Jhanjharpur road in km 0.0 to 11.64 in darbhanga district under Road Division, Benipur for the year 2019-20 | C26: EE,RCD BENIPUR, DARBHANGA | D26: =1437.98+367.3+413.37 -> 2218.65 | H26: 31208.216 | J26: 16.659 | K26: 788.84 | M26: 510.05 | N26: =K26+L26+M26 -> 1298.89 | Q26: 1489.1 | R26: 1007.42 | S26: =O26+P26+Q26+R26 -> 2496.52 | AC26: 18 SBD of 2019-20 dt. 13.03.2020 | AD26: QTY PAGE 16/70 | AE26: Page no 111
A27: 2021-22 | B27: Widening & Strengthening of Supaul to Bauram Road in Km 0.00 to 12.20 under Road Division Benipur for the year 2019-20 | C27: EE,RCD BENIPUR, DARBHANGA | D27: =119.83+228.99+588.873+172.46+1006.31 -> 2116.463 | E27: 48.181 | H27: =16115.27+1648.73 -> 17764 | K27: 6988.78 | N27: =K27+L27+M27 -> 6988.78 | S27: =O27+P27+Q27+R27 -> 0 | AC27: 04SBD/2020-21 dt 20.07.2020 | AD27: QTY PAGE 17&18/70 | AE27: Page no 23-24
A28: 2021-22 | B28: Widening and Strengthening (from Single Lane to Double Lane) of Turki (N.H.-77)-Saraiya (N.H.-102) Road (Km 0.000 to Km 21.825) under PMGSY (RCP-LWE) in the district of Muzaffarpur, Bihar for the year 2019-20 (Package No. BR23RC-119 ) | C28: EE, RCD, RD-1, Muzaffarpur | D28: =641.41+1622.88+35+9+16.5+24.02+131.49 -> 2480.3 | E28: 16.8748 | K28: 9345 | M28: 9146.48 | N28: =K28+L28+M28 -> 18491.48 | Q28: 1420.57 | S28: =O28+P28+Q28+R28 -> 1420.57 | AC28: SBD-09 LWE OF 2020-21 DT 1112.2020 | AD28: QTY PAGE 19/70 | AE28: Page no 114
A29: 2021-22 | B29: Widening & Strengthening of Magardahi Ghat to Siliut (Durga Asthan) road in Km. 0.00 to 5.00 (Total Length 5.00 Km) for the Year 2019-20 | C29: EE, RCD, SAMASTIPUR | H29: 75923.11 | K29: 3882.51 | M29: 7778.12 | N29: =K29+L29+M29 -> 11660.63 | Q29: 836.94 | R29: 0 | S29: =O29+P29+Q29+R29 -> 836.94 | V29: 4287.975 | AC29: 08/EPC of 2020-21 dt. 24.12.2020 | AD29: QTY PAGE 20/70 | AE29: Page no 115
A30: 2021-22 | B30: Widening & Strengthening of Muktapur-Warisnagar-Bhadohighat-Hatauri Road in Km. 00 to 23.300 (Total Length - 23.30 Km) for the year 2019-20 | C30: EE, RCD, SAMASTIPUR | D30: =5605.85+428.51 -> 6034.36 | H30: 13099 | K30: 4368.06 | M30: 8849.9 | N30: =K30+L30+M30 -> 13217.96 | Q30: 1690.33 | R30: 0 | S30: =O30+P30+Q30+R30 -> 1690.33 | AC30: 07/SBD of 2020-21 dt. 22.09.2020 | AD30: QTY PAGE 21/70 | AE30: Page no 116
A31: 2021-22 | B31: Construction and upgradation of existing Road along Indo-Nepal Border Road Project from Kanhauli to Sursand (Length=49.150 km) Under Sitamarhi District for the year 2019-20 | C31: EE, RCD, SITAMARHI | D31: =57.24+367.92 -> 425.16 | E31: 24.143 | H31: =502680.98+37200+1057.14 -> 540938.12 | K31: 13605 | M31: 3429.375 | N31: =K31+L31+M31 -> 17034.375 | S31: =O31+P31+Q31+R31 -> 0 | AC31: 02SBD/2021-22 DATED 24.06.2021 | AD31: QTY PAGE 26/70 | AE31: INBR EXP CERTIFICAT QTY 12032025.pdf
A32: 2021-22 | B32: Civil Works including Building and U.G.Piping Works for HURL Project, Barauni. SUBCONTRACT FROM TECHNIP INDIA LIMITED | C32: Technip India Limited | D32: 6743.308 | E32: 224 | F32: 245.009 | H32: 3447.921 | L32: 1498.309 | N32: =K32+L32+M32 -> 1498.309 | S32: =O32+P32+Q32+R32 -> 0 | AC32: C100006467 dated 07.01.19 Ammend-7 dt. 30.05.2023 | AD32: QTY PAGE 54/70
A33: 2021-22 | B33: Subcontract for Piling Works for OHCU Project, IOCL Barauni | C33: Technip Energies India Limited, NOIDA | D33: =PI()*0.5^2/4*11454 -> 2248.9876 | N33: =K33+L33+M33 -> 0 | S33: =O33+P33+Q33+R33 -> 0 | W33: 11454 | AC33: C100008901 DT. 19.06.2021 ammendment 3 dt. 16.03.2023 RA BILL 09 TILL 31.03.22 | AD33: QTY PAGE 56/70
A34: 2021-22 | B34: Subcontract for Piling Works of DHDT Unit at IOCL BARAUNI | C34: CB&I India Private Limited (MCDERMOTT) | D34: =PI()*0.5^2/4*8541 -> 1677.0214 | E34: 279 | N34: =K34+L34+M34 -> 0 | S34: =O34+P34+Q34+R34 -> 0 | W34: 8541 | AC34: 356420-SC-03/540493 DT. 04.08.2021 CHANGE ORDER-03 DT. 17.11.20223 | AD34: QTY PAGE 66&67/70 | AE34: Page no 85-86
A35: 2021-22 | B35: Subcontract for Piling Work for NHT-ll + ISOM-ll Unit at IOCL, Barauni, Bihar | C35: CB&I India Private Limited (MCDERMOTT) | D35: =PI()*0.5^2/4*4161 -> 817.01044 | E35: 175.02 | N35: =K35+L35+M35 -> 0 | S35: =O35+P35+Q35+R35 -> 0 | W35: 4161 | AC35: 241222-SC-04/560515 DT. 12.11.2021 CHANGE ORDER-04 DT. 03.04.2024 | AD35: QTY PAGE 69&70/70 | AE35: Page No 94-95
A36: 2021-22 | B36: =CONCATENATE(1,B20,",",2,B21,",",3,B22,",",4,B23,",",5,B24,",",6,B25,",",7,B26,",",8,B27,",",9,B28,",",10,B29,",",11,B30,",",12,B31,",",13,B32,",",14,B33,",",15,B34,",",16,B35) -> 1RESTORATION AND LINING OF SONE WESTERN LINK CANAL,2CONSTRUCTION OF CANAL AND ITS LINING WORK AND STRUCTURES FROM R.D. 806.40 TO R.D. 827.70 UNDER TIRHUT MAIN CANAL,3Lining work of Chausa Branch Canal from 0.000 Km to 12.924 Km & Restoration of Kochas and Indaur Distributary under Ganga Pump Canal Division, Chausa Buxar,4Widening and Strenthening of Road from Basariya, NH-28 to Sarairanjan, NH-103 via Ramnagar chowk (Bella-Megh chowk), Jhakhra, Sarairanjan, Saraiya, Morwa under Road Division, Rosera from Ch. Km. 5.600 to 12.270 for the year 2018-19.,5Widening & Strengthening work of Vishwakarma Chowk to Guabadi,Narayanpipar, Chaurahi Block Head Via-Bakhadda Chowk of Cheriya Bariyarpur Block for the year 2019-20.,6 Long Term Output and Performance based Road Maintenance work for the roads Package No.9A/OPRMC2/Benipur.,7Widening & Strengthening of Dharraura Chowk to Mazampur Bajidpur-Bahera Jhanjharpur road in km 0.0 to 11.64 in darbhanga district under Road Division, Benipur for the year 2019-20,8Widening & Strengthening of Supaul to Bauram Road in Km 0.00 to 12.20 under Road Division Benipur for the year 2019-20,9Widening and Strengthening (from Single Lane to Double Lane) of Turki (N.H.-77)-Saraiya (N.H.-102) Road (Km 0.000 to Km 21.825) under PMGSY (RCP-LWE) in the district of Muzaffarpur, Bihar for the year 2019-20 (Package No. BR23RC-119 ),10Widening & Strengthening of Magardahi Ghat to Siliut (Durga Asthan) road in Km. 0.00 to 5.00 (Total Length 5.00 Km) for the Year 2019-20,11Widening & Strengthening of Muktapur-Warisnagar-Bhadohighat-Hatauri Road in Km. 00 to 23.300 (Total Length - 23.30 Km) for the year 2019-20,12Construction and upgradation of existing Road along Indo-Nepal Border Road Project from Kanhauli to Sursand (Length=49.150 km) Under Sitamarhi District for the year 2019-20,13Civil Works including Building and U.G.Piping Works for HURL Project, Barauni. SUBCONTRACT FROM TECHNIP INDIA LIMITED,14Subcontract for Piling Works for OHCU Project, IOCL Barauni,15Subcontract for Piling Works of DHDT Unit at IOCL BARAUNI,16Subcontract for Piling Work for NHT-ll + ISOM-ll Unit at IOCL, Barauni, Bihar | C36: =CONCATENATE(1,C20,",",2,C21,",",3,C22,",",4,C23,",",5,C24,",",6,C25,",",7,C26,",",8,C27,",",9,C28,",",10,C29,",",11,C30,",",12,C31,",",13,C32,",",14,C33,",",15,C34,",",16,C35) -> 1EE, SONE BARRAGE DIVISION, INDRAPURI,2EE, Tirhut Canal Division, Motipur, Camp- Muzaffarpur,3EE, GANGA PUMP CANAL DIVISION, BUXAR,4EE, RCD, ROSERA,5EE, RCD, BEGUSARAI,6EE,RCD BENIPUR, DARBHANGA,7EE,RCD BENIPUR, DARBHANGA,8EE,RCD BENIPUR, DARBHANGA,9EE, RCD, RD-1, Muzaffarpur,10EE, RCD, SAMASTIPUR,11EE, RCD, SAMASTIPUR,12EE, RCD, SITAMARHI,13Technip India Limited,14Technip Energies India Limited, NOIDA,15CB&I India Private Limited (MCDERMOTT),16CB&I India Private Limited (MCDERMOTT) | D36: =SUM(D20:D35) -> 53917.179 | E36: =SUM(E20:E35) -> 768.4758 | F36: =SUM(F20:F35) -> 2314.955 | G36: =SUM(G20:G35) -> 0 | H36: =SUM(H20:H35) -> 1231155.9 | I36: =SUM(I20:I35) -> 14223.012 | J36: =SUM(J20:J35) -> 16.659 | K36: =SUM(K20:K35) -> 53137.913 | ... AB36: =SUM(AB20:AB35) -> 26981994 | AC36: =CONCATENATE(AC20,",",AC21,",",AC22,",",AC23,",",AC24,",",AC25,",",AC26,",",AC27,",",AC28,",",AC29,",",AC30,",",AC31,",",AC32,",",AC33,",",AC34,",",AC35) -> 02/SBD/2016-17 DATED 2.2.2017 BLPL SHARE 27.5%+69.7% subcontract from Lead Member of JV),01/SBD/2017-18 DATED 22.11.2017,01/SBD/2017-18 DATED 4.11.2017,01 (SBD) of 2020-21 dt. 29.05.2020,03/2019-20 DT. 04.12.2019,4/MBD/2018-19 DT. 12.02.2019,18 SBD of 2019-20 dt. 13.03.2020,04SBD/2020-21 dt 20.07.2020,SBD-09 LWE OF 2020-21 DT 1112.2020,08/EPC of 2020-21 dt. 24.12.2020,07/SBD of 2020-21 dt. 22.09.2020,02SBD/2021-22 DATED 24.06.2021,C100006467 dated 07.01.19 Ammend-7 dt. 30.05.2023,C100008901 DT. 19.06.2021 ammendment 3 dt. 16.03.2023 RA BILL 09 TILL 31.03.22,356420-SC-03/540493 DT. 04.08.2021 CHANGE ORDER-03 DT. 17.11.20223,241222-SC-04/560515 DT. 12.11.2021 CHANGE ORDER-04 DT. 03.04.2024
A37: 2022-23 | B37: RESTORATION AND LINING OF SONE WESTERN LINK CANAL | C37: EE, SONE BARRAGE DIVISION, INDRAPURI | D37: =(3069.28+872.1)*(27.5%+69.7%) -> 3831.0214 | E37: 64.499 | H37: =12845.518*(27.5%+69.7%) -> 12485.843 | I37: =31998.87*(27.5%+69.7%) -> 31102.902 | K37: =97.132*(27.5%+69.7%) -> 94.412304 | N37: =K37+L37+M37 -> 94.412304 | S37: =O37+P37+Q37+R37 -> 0 | V37: =360*(27.5%+69.7%) -> 349.92 | AC37: 02/SBD/2016-17 DATED 2.2.2017 BLPL SHARE 27.5%+69.7% subcontract from Lead Member of JV) | AD37: QTY PAGE 8/70
A38: 2022-23 | B38: CONSTRUCTION OF CANAL AND ITS LINING WORK AND STRUCTURES FROM R.D. 806.40 TO R.D. 827.70 UNDER TIRHUT MAIN CANAL | C38: EE, Tirhut Canal Division, Motipur, Camp- Muzaffarpur | D38: =3131.93+1880.36 -> 5012.29 | F38: 507.5 | H38: 34920.89 | N38: =K38+L38+M38 -> 0 | S38: =O38+P38+Q38+R38 -> 0 | AC38: 01/SBD/2017-18 DATED 22.11.2017 | AD38: QTY PAGE 9/70 | AE38: WRD MOTIPUR WORK DONE CERTIFICATE 19052025.pdf
A39: 2022-23 | B39: Lining work of Chausa Branch Canal from 0.000 Km to 12.924 Km & Restoration of Kochas and Indaur Distributary under Ganga Pump Canal Division, Chausa Buxar | C39: EE, GANGA PUMP CANAL DIVISION, BUXAR | D39: =6066.004+243.714 -> 6309.718 | F39: 1809.43 | H39: 11983.547 | N39: =K39+L39+M39 -> 0 | S39: =O39+P39+Q39+R39 -> 0 | AC39: 01/SBD/2017-18 DATED 4.11.2017 | AD39: QTY PAGE 10/70 | AE39: Page no 105
A40: 2022-23 | B40: Long Term Output and Performance based Road Maintenance work for the roads Package No.9A/OPRMC2/Benipur. | C40: EE,RCD BENIPUR, DARBHANGA | D40: 305.216 | H40: 0 | J40: 0 | K40: 78.812 | M40: 0 | N40: =K40+L40+M40 -> 78.812 | R40: 0 | S40: =O40+P40+Q40+R40 -> 0 | Y40: 0 | AC40: 4/MBD/2018-19 DT. 12.02.2019 | AD40: QTY PAGE 22/70 | AE40: Page no 117
A41: 2022-23 | B41: Widening & Strengthening of Supaul to Bauram Road in Km 0.00 to 12.20 under Road Division Benipur for the year 2019-20 | C41: EE,RCD BENIPUR, DARBHANGA | D41: =456.163+1064.086+1182.369+591.688+341.7+1889.25 -> 5525.256 | E41: 85.032 | H41: 29340.904 | K41: 9009.054 | M41: 11007.124 | N41: =K41+L41+M41 -> 20016.178 | Q41: 2238.48 | R41: 1121.726 | S41: =O41+P41+Q41+R41 -> 3360.206 | AC41: 04SBD/2020-21 dt 20.07.2020 | AD41: QTY PAGE 17&18/70
A42: 2022-23 | B42: Widening and Strengthening (from Single Lane to Double Lane) of Turki (N.H.-77)-Saraiya (N.H.-102) Road (Km 0.000 to Km 21.825) under PMGSY (RCP-LWE) in the district of Muzaffarpur, Bihar for the year 2019-20 (Package No. BR23RC-119 ) | C42: EE, RCD, RD-1, Muzaffarpur | D42: =660.4+189.3+157.99+16.96+285.38 -> 1310.03 | E42: 79.1129 | H42: 60567.535 | K42: 3613.6 | M42: 4134.85 | N42: =K42+L42+M42 -> 7748.45 | P42: 4495.67 | Q42: 6438.07 | S42: =O42+P42+Q42+R42 -> 10933.74 | AC42: SBD-09 LWE OF 2020-21 DT 1112.2020 | AD42: QTY PAGE 19/70 | AE42: Page no 114
A43: 2022-23 | B43: Widening & Strengthening of Magardahi Ghat to Siliut (Durga Asthan) road in Km. 0.00 to 5.00 (Total Length 5.00 Km) for the Year 2019-20 | C43: EE, RCD, SAMASTIPUR | D43: 0 | K43: 204.36 | M43: 952.54 | N43: =K43+L43+M43 -> 1156.9 | Q43: 1260.51 | R43: 1056.775 | S43: =O43+P43+Q43+R43 -> 2317.285 | V43: 1091.2 | AC43: 08/EPC of 2020-21 dt. 24.12.2020 | AD43: QTY PAGE 20/70 | AE43: Page no 115
A44: 2022-23 | B44: Widening & Strengthening of Muktapur-Warisnagar-Bhadohighat-Hatauri Road in Km. 00 to 23.300 (Total Length - 23.30 Km) for the year 2019-20 | C44: EE, RCD, SAMASTIPUR | D44: =3319.87+475.445 -> 3795.315 | H44: 56053.123 | K44: 1949.61 | M44: 6754.9 | N44: =K44+L44+M44 -> 8704.51 | Q44: 3146.911 | R44: 2698.88 | S44: =O44+P44+Q44+R44 -> 5845.791 | AC44: 07/SBD of 2020-21 dt. 22.09.2020 | AD44: QTY PAGE 21/70 | AE44: Page no 116
A45: 2022-23 | B45: Construction and upgradation of existing Road along Indo-Nepal Border Road Project from Kanhauli to Sursand (Length=49.150 km) Under Sitamarhi District for the year 2019-20 | C45: EE, RCD, SITAMARHI | D45: =264.84+1944.72+64.8+178.5 -> 2452.86 | E45: 127.576 | H45: =38894.02+31457.25+1385.191 -> 71736.461 | K45: 10413.6 | M45: 3391.875 | N45: =K45+L45+M45 -> 13805.475 | S45: =O45+P45+Q45+R45 -> 0 | U45: 151.2 | AC45: 02SBD/2021-22 DATED 24.06.2021 | AD45: QTY PAGE 26/70 | AE45: INBR EXP CERTIFICAT QTY 12032025.pdf
A46: 2022-23 | B46: Civil Works including Building and U.G.Piping Works for HURL Project, Barauni. SUBCONTRACT FROM TECHNIP INDIA LIMITED | C46: Technip India Limited | D46: 2213.557 | E46: 165 | H46: 1119.068 | L46: 1012.762 | N46: =K46+L46+M46 -> 1012.762 | S46: =O46+P46+Q46+R46 -> 0 | AC46: C100006467 dated 07.01.19 Ammend-7 dt. 30.05.2023 | AD46: QTY PAGE 55/70
A47: 2022-23 | B47: Subcontract for Piling Works for OHCU Project, IOCL Barauni | C47: Technip Energies India Limited, NOIDA | D47: =PI()*0.5^2/4*7349 -> 1442.9728 | E47: 374 | N47: =K47+L47+M47 -> 0 | S47: =O47+P47+Q47+R47 -> 0 | W47: 7349 | AC47: C100008901 DT. 19.06.2021 ammendment 3 dt. 16.03.2023 RA BILL 15 TILL 31.03.23 | AD47: QTY PAGE (59-56)/70
A48: 2022-23 | B48: Subcontract for Piling Works of DHDT Unit at IOCL BARAUNI | C48: CB&I India Private Limited (MCDERMOTT) | D48: =PI()*0.5^2/4*20759 -> 4076.0201 | E48: 483.06 | N48: =K48+L48+M48 -> 0 | S48: =O48+P48+Q48+R48 -> 0 | W48: 20759.24 | AC48: 356420-SC-03/540493 DT. 04.08.2021 CHANGE ORDER-03 DT. 17.11.20223 | AD48: QTY PAGE 66&67/70 | AE48: Page no 85-86
A49: 2022-23 | B49: Subcontract for Piling Work for NHT-ll + ISOM-ll Unit at IOCL, Barauni, Bihar | C49: CB&I India Private Limited (MCDERMOTT) | D49: =PI()*0.5^2/4*10817 -> 2123.913 | E49: 277.33 | N49: =K49+L49+M49 -> 0 | S49: =O49+P49+Q49+R49 -> 0 | W49: 10817 | AC49: 241222-SC-04/560515 DT. 12.11.2021 CHANGE ORDER-04 DT. 03.04.2024 | AD49: QTY PAGE 69&70/70 | AE49: Page No 94-95
A50: 2022-23 | B50: =CONCATENATE(1,B37,",",2,B38,",",3,B39,",",4,B40,",",5,B41,",",6,B42,",",7,B43,",",8,B44,",",9,B45,",",10,B46,",",11,B47,",",12,B48,",",13,B49) -> 1RESTORATION AND LINING OF SONE WESTERN LINK CANAL,2CONSTRUCTION OF CANAL AND ITS LINING WORK AND STRUCTURES FROM R.D. 806.40 TO R.D. 827.70 UNDER TIRHUT MAIN CANAL,3Lining work of Chausa Branch Canal from 0.000 Km to 12.924 Km & Restoration of Kochas and Indaur Distributary under Ganga Pump Canal Division, Chausa Buxar,4 Long Term Output and Performance based Road Maintenance work for the roads Package No.9A/OPRMC2/Benipur.,5Widening & Strengthening of Supaul to Bauram Road in Km 0.00 to 12.20 under Road Division Benipur for the year 2019-20,6Widening and Strengthening (from Single Lane to Double Lane) of Turki (N.H.-77)-Saraiya (N.H.-102) Road (Km 0.000 to Km 21.825) under PMGSY (RCP-LWE) in the district of Muzaffarpur, Bihar for the year 2019-20 (Package No. BR23RC-119 ),7Widening & Strengthening of Magardahi Ghat to Siliut (Durga Asthan) road in Km. 0.00 to 5.00 (Total Length 5.00 Km) for the Year 2019-20,8Widening & Strengthening of Muktapur-Warisnagar-Bhadohighat-Hatauri Road in Km. 00 to 23.300 (Total Length - 23.30 Km) for the year 2019-20,9Construction and upgradation of existing Road along Indo-Nepal Border Road Project from Kanhauli to Sursand (Length=49.150 km) Under Sitamarhi District for the year 2019-20,10Civil Works including Building and U.G.Piping Works for HURL Project, Barauni. SUBCONTRACT FROM TECHNIP INDIA LIMITED,11Subcontract for Piling Works for OHCU Project, IOCL Barauni,12Subcontract for Piling Works of DHDT Unit at IOCL BARAUNI,13Subcontract for Piling Work for NHT-ll + ISOM-ll Unit at IOCL, Barauni, Bihar | C50: =CONCATENATE(1,C37,",",2,C38,",",3,C39,",",4,C40,",",5,C41,",",6,C42,",",7,C43,",",8,C44,",",9,C45,",",10,C46,",",11,C47,",",12,C48,",",13,C49) -> 1EE, SONE BARRAGE DIVISION, INDRAPURI,2EE, Tirhut Canal Division, Motipur, Camp- Muzaffarpur,3EE, GANGA PUMP CANAL DIVISION, BUXAR,4EE,RCD BENIPUR, DARBHANGA,5EE,RCD BENIPUR, DARBHANGA,6EE, RCD, RD-1, Muzaffarpur,7EE, RCD, SAMASTIPUR,8EE, RCD, SAMASTIPUR,9EE, RCD, SITAMARHI,10Technip India Limited,11Technip Energies India Limited, NOIDA,12CB&I India Private Limited (MCDERMOTT),13CB&I India Private Limited (MCDERMOTT) | D50: =SUM(D37:D49) -> 38398.169 | E50: =SUM(E37:E49) -> 1655.6099 | F50: =SUM(F37:F49) -> 2316.93 | G50: =SUM(G37:G49) -> 0 | H50: =SUM(H37:H49) -> 278207.37 | I50: =SUM(I37:I49) -> 31102.902 | J50: =SUM(J37:J49) -> 0 | K50: =SUM(K37:K49) -> 25363.448 | ... AB50: =SUM(AB37:AB49) -> 0 | AC50: =CONCATENATE(AC37,",",AC38,",",AC39,",",AC40,",",AC41,",",AC42,",",AC43,",",AC44,",",AC45,",",AC46,",",AC47,",",AC48,",",AC49) -> 02/SBD/2016-17 DATED 2.2.2017 BLPL SHARE 27.5%+69.7% subcontract from Lead Member of JV),01/SBD/2017-18 DATED 22.11.2017,01/SBD/2017-18 DATED 4.11.2017,4/MBD/2018-19 DT. 12.02.2019,04SBD/2020-21 dt 20.07.2020,SBD-09 LWE OF 2020-21 DT 1112.2020,08/EPC of 2020-21 dt. 24.12.2020,07/SBD of 2020-21 dt. 22.09.2020,02SBD/2021-22 DATED 24.06.2021,C100006467 dated 07.01.19 Ammend-7 dt. 30.05.2023,C100008901 DT. 19.06.2021 ammendment 3 dt. 16.03.2023 RA BILL 15 TILL 31.03.23,356420-SC-03/540493 DT. 04.08.2021 CHANGE ORDER-03 DT. 17.11.20223,241222-SC-04/560515 DT. 12.11.2021 CHANGE ORDER-04 DT. 03.04.2024
A51: 2023-24 | B51: CONSTRUCTION OF CANAL AND ITS LINING WORK AND STRUCTURES FROM R.D. 806.40 TO R.D. 827.70 UNDER TIRHUT MAIN CANAL | C51: EE, Tirhut Canal Division, Motipur, Camp- Muzaffarpur | D51: =3319.6+2844.65 -> 6164.25 | F51: 1060.39 | H51: 16161.47 | N51: =K51+L51+M51 -> 0 | S51: =O51+P51+Q51+R51 -> 0 | AC51: 01/SBD/2017-18 DATED 22.11.2017 | AD51: QTY PAGE 9/70 | AE51: WRD MOTIPUR WORK DONE CERTIFICATE 19052025.pdf
A52: 2023-24 | B52: Lining work of Chausa Branch Canal from 0.000 Km to 12.924 Km & Restoration of Kochas and Indaur Distributary under Ganga Pump Canal Division, Chausa Buxar | C52: EE, GANGA PUMP CANAL DIVISION, BUXAR | D52: =4571+259.915 -> 4830.915 | F52: 2207.58 | H52: 93270 | N52: =K52+L52+M52 -> 0 | S52: =O52+P52+Q52+R52 -> 0 | AC52: 01/SBD/2017-18 DATED 4.11.2017 | AD52: QTY PAGE 10/70 | AE52: lt no 656 dt 03.06.25 Performance cert.pdf
A53: 2023-24 | B53: Widening & Strengthening of Supaul to Bauram Road in Km 0.00 to 12.20 under Road Division Benipur for the year 2019-20 | C53: EE,RCD BENIPUR, DARBHANGA | D53: =888.696+90.06 -> 978.756 | H53: 2691.84 | K53: 404.449 | N53: =K53+L53+M53 -> 404.449 | Q53: 403.646 | R53: 198.22 | S53: =O53+P53+Q53+R53 -> 601.866 | V53: 121.452 | AC53: 04SBD/2020-21 dt 20.07.2020 | AD53: QTY PAGE 17&18/70 | AE53: Page no 23-24
A54: 2023-24 | B54: Widening & Strengthening of Magardahi Ghat to Siliut (Durga Asthan) road in Km. 0.00 to 5.00 (Total Length 5.00 Km) for the Year 2019-20 | C54: EE, RCD, SAMASTIPUR | D54: 0 | N54: =K54+L54+M54 -> 0 | S54: =O54+P54+Q54+R54 -> 0 | V54: 1800 | AC54: 08/EPC of 2020-21 dt. 24.12.2020 | AD54: QTY PAGE 20/70 | AE54: Page no 115
A55: 2023-24 | B55: Widening & Strengthening of Muktapur-Warisnagar-Bhadohighat-Hatauri Road in Km. 00 to 23.300 (Total Length - 23.30 Km) for the year 2019-20 | C55: EE, RCD, SAMASTIPUR | H55: 24088.967 | N55: =K55+L55+M55 -> 0 | S55: =O55+P55+Q55+R55 -> 0 | AC55: 07/SBD of 2020-21 dt. 22.09.2020 | AD55: QTY PAGE 21/70 | AE55: Page no 116
A56: 2023-24 | B56: Construction and upgradation of existing Road along Indo-Nepal Border Road Project from Kanhauli to Sursand (Length=49.150 km) Under Sitamarhi District for the year 2019-20 | C56: EE, RCD, SITAMARHI | D56: =792.52+4286.79+103.68+243.6 -> 5426.59 | E56: 364.7334 | H56: =395809.49+219667.08+5390.384 -> 620866.95 | K56: 45607.8 | M56: 26367.965 | N56: =K56+L56+M56 -> 71975.765 | P56: 1802.85 | Q56: 5150.95 | S56: =O56+P56+Q56+R56 -> 6953.8 | U56: 1209.6 | AC56: 02SBD/2021-22 DATED 24.06.2021 | AD56: QTY PAGE 26/70 | AE56: INBR EXP CERTIFICAT QTY 12032025.pdf
A57: 2023-24 | B57: Subcontract for Piling Works for OHCU Project, IOCL Barauni | C57: Technip Energies India Limited, NOIDA | D57: =PI()*0.5^2/4*191 -> 37.502762 | N57: =K57+L57+M57 -> 0 | S57: =O57+P57+Q57+R57 -> 0 | W57: 191 | AC57: C100008901 DT. 19.06.2021 ammendment 3 dt. 16.03.2023 RA BILL 17 FINAL BILL | AD57: QTY PAGE (62-59)/70
A58: 2023-24 | B58: Subcontract for Piling Work for NHT-ll + ISOM-ll Unit at IOCL, Barauni, Bihar | C58: CB&I India Private Limited (MCDERMOTT) | D58: =PI()*0.5^2/4*1226 -> 240.72454 | E58: 224.13 | H58: 4394 | N58: =K58+L58+M58 -> 0 | S58: =O58+P58+Q58+R58 -> 0 | W58: 1225.83 | X58: 3.02 | AC58: 241222-SC-04/560515 DT. 12.11.2021 CHANGE ORDER-04 DT. 03.04.2024 | AD58: QTY PAGE 69&70/70 | AE58: Page no 85-86
A59: 2023-24 | B59: =CONCATENATE(1,B53,",",2,B54,",",3,B55,",",4,B56,",",5,B57,",",6,B58) -> 1Widening & Strengthening of Supaul to Bauram Road in Km 0.00 to 12.20 under Road Division Benipur for the year 2019-20,2Widening & Strengthening of Magardahi Ghat to Siliut (Durga Asthan) road in Km. 0.00 to 5.00 (Total Length 5.00 Km) for the Year 2019-20,3Widening & Strengthening of Muktapur-Warisnagar-Bhadohighat-Hatauri Road in Km. 00 to 23.300 (Total Length - 23.30 Km) for the year 2019-20,4Construction and upgradation of existing Road along Indo-Nepal Border Road Project from Kanhauli to Sursand (Length=49.150 km) Under Sitamarhi District for the year 2019-20,5Subcontract for Piling Works for OHCU Project, IOCL Barauni,6Subcontract for Piling Work for NHT-ll + ISOM-ll Unit at IOCL, Barauni, Bihar | C59: =CONCATENATE(1,C53,",",2,C54,",",3,C55,",",4,C56,",",5,C57,",",6,C58) -> 1EE,RCD BENIPUR, DARBHANGA,2EE, RCD, SAMASTIPUR,3EE, RCD, SAMASTIPUR,4EE, RCD, SITAMARHI,5Technip Energies India Limited, NOIDA,6CB&I India Private Limited (MCDERMOTT) | D59: =SUM(D51:D58) -> 17678.738 | E59: =SUM(E51:E58) -> 588.8634 | F59: =SUM(F51:F58) -> 3267.97 | G59: =SUM(G51:G58) -> 0 | H59: =SUM(H51:H58) -> 761473.23 | I59: =SUM(I51:I58) -> 0 | J59: =SUM(J51:J58) -> 0 | K59: =SUM(K51:K58) -> 46012.249 | ... AB59: =SUM(AB51:AB58) -> 0 | AC59: =CONCATENATE(AC53,",",AC54,",",AC55,",",AC56,",",AC57,",",AC58) -> 04SBD/2020-21 dt 20.07.2020,08/EPC of 2020-21 dt. 24.12.2020,07/SBD of 2020-21 dt. 22.09.2020,02SBD/2021-22 DATED 24.06.2021,C100008901 DT. 19.06.2021 ammendment 3 dt. 16.03.2023 RA BILL 17 FINAL BILL,241222-SC-04/560515 DT. 12.11.2021 CHANGE ORDER-04 DT. 03.04.2024
A60: 2024-25 | B60: CONSTRUCTION OF CANAL AND ITS LINING WORK AND STRUCTURES FROM R.D. 806.40 TO R.D. 827.70 UNDER TIRHUT MAIN CANAL | C60: EE, Tirhut Canal Division, Motipur, Camp- Muzaffarpur | D60: =1848.97+607.85 -> 2456.82 | F60: 512.4 | H60: 153569.22 | N60: =K60+L60+M60 -> 0 | S60: =O60+P60+Q60+R60 -> 0 | AC60: 01/SBD/2017-18 DATED 22.11.2017 | AD60: WRD MOTIPUR WORK DONE CERTIFICATE 19052025.pdf
A61: 2024-25 | B61: Lining work of Chausa Branch Canal from 0.000 Km to 12.924 Km & Restoration of Kochas and Indaur Distributary under Ganga Pump Canal Division, Chausa Buxar | C61: EE, GANGA PUMP CANAL DIVISION, BUXAR | D61: =4150.72+207.4 -> 4358.12 | F61: 1353.969 | H61: 24268.01 | N61: =K61+L61+M61 -> 0 | S61: =O61+P61+Q61+R61 -> 0 | AC61: 01/SBD/2017-18 DATED 4.11.2017 | AD61: lt no 656 dt 03.06.25 Performance cert.pdf
A62: 2024-25 | B62: Construction and upgradation of existing Road along Indo-Nepal Border Road Project from Kanhauli to Sursand (Length=49.150 km) Under Sitamarhi District for the year 2019-20 | C62: EE, RCD, SITAMARHI | D62: =64.8+126 -> 190.8 | H62: =186553.56+182439.58+2717.346 -> 371710.49 | K62: 68802.671 | M62: 42824.685 | N62: =K62+L62+M62 -> 111627.36 | P62: 3813.832 | Q62: 6127.94 | S62: =O62+P62+Q62+R62 -> 9941.772 | AC62: 02SBD/2021-22 DATED 24.06.2021 | AD62: INBR EXP CERTIFICAT QTY 12032025.pdf
A63: 2024-25 | B63: Restoration Work of Saran Main Canal From K.m. 0.00 to K.M. 17.00 | C63: EE, SMC DIVISION, GOPALGANJ | D63: 35728.059 | H63: 1284228 | I63: 27890.68 | N63: =K63+L63+M63 -> 0 | S63: =O63+P63+Q63+R63 -> 0 | U63: 49716.66 | AD63: SMC EXPERIENCE CERTIFICATE 20052025 CamScanner 05-20-2025 14.29.pdf
A64: 2024-25 | B64: Widening & Strengthening of Muktapur-Warisnagar-Bhadohighat-Hatauri Road in Km. 00 to 23.300 (Total Length - 23.30 Km) for the year 2019-20 | C64: EE, RCD, SAMASTIPUR | D64: 732.28 | H64: 15162.38 | AD64: Page no 116
A65: 2024-25 | B65: Widening & Strengthening of Magardahi Ghat to Siliut (Durga Asthan) road in Km. 0.00 to 5.00 (Total Length 5.00 Km) for the Year 2019-20 | C65: EE, RCD, SAMASTIPUR | H65: 2437.23 | R65: 0.45 | S65: =O65+P65+Q65+R65 -> 0.45 | V65: 318
N66: =K66+L66+M66 -> 0 | S66: =O66+P66+Q66+R66 -> 0
N67: =K67+L67+M67 -> 0 | S67: =O67+P67+Q67+R67 -> 0
A68: 2024-25 | B68: =CONCATENATE(1,B60,",",2,B61,",",3,B62,",",4,B63,",",5,B66,",",6,B67) -> 1CONSTRUCTION OF CANAL AND ITS LINING WORK AND STRUCTURES FROM R.D. 806.40 TO R.D. 827.70 UNDER TIRHUT MAIN CANAL,2Lining work of Chausa Branch Canal from 0.000 Km to 12.924 Km & Restoration of Kochas and Indaur Distributary under Ganga Pump Canal Division, Chausa Buxar,3Construction and upgradation of existing Road along Indo-Nepal Border Road Project from Kanhauli to Sursand (Length=49.150 km) Under Sitamarhi District for the year 2019-20,4Restoration Work of Saran Main Canal From K.m. 0.00 to K.M. 17.00,5,6 | C68: =CONCATENATE(1,C60,",",2,C61,",",3,C62,",",4,C63,",",5,C66,",",6,C67) -> 1EE, Tirhut Canal Division, Motipur, Camp- Muzaffarpur,2EE, GANGA PUMP CANAL DIVISION, BUXAR,3EE, RCD, SITAMARHI,4EE, SMC DIVISION, GOPALGANJ,5,6 | D68: =SUM(D60:D67) -> 43466.079 | E68: =SUM(E60:E67) -> 0 | F68: =SUM(F60:F67) -> 1866.369 | G68: =SUM(G60:G67) -> 0 | H68: =SUM(H60:H67) -> 1851375.4 | I68: =SUM(I60:I67) -> 27890.68 | J68: =SUM(J60:J67) -> 0 | K68: =SUM(K60:K67) -> 68802.671 | ... AB68: =SUM(AB60:AB67) -> 0 | AC68: =CONCATENATE(AC60,",",AC61,",",AC62,",",AC63,",",AC66,",",AC67) -> 01/SBD/2017-18 DATED 22.11.2017,01/SBD/2017-18 DATED 4.11.2017,02SBD/2021-22 DATED 24.06.2021,,,
A69: MAX | B69: in any 1 year during last 5 year 2020-2021 TO 2024-2025 | D69: =MAX(D5:D68) -> 53917.179 | E69: =MAX(E5:E68) -> 1655.6099 | F69: =MAX(F5:F68) -> 3267.97 | G69: =MAX(G5:G68) -> 0 | H69: =MAX(H5:H68) -> 1851375.4 | I69: =MAX(I5:I68) -> 31102.902 | J69: =MAX(J5:J68) -> 6798.726 | K69: =MAX(K5:K68) -> 68802.671 | ... AB69: =MAX(AB5:AB68) -> 48597927
B71: TOTAL DURING LAST 5 YRS | D71: =D19+D36+D50+D59+D68 -> 207120.78 | E71: =E19+E36+E50+E59+E68 -> 3585.9491 | F71: =F19+F36+F50+F59+F68 -> 11887.702 | G71: =G19+G36+G50+G59+G68 -> 0 | H71: =H19+H36+H50+H59+H68 -> 5535600.6 | I71: =I19+I36+I50+I59+I68 -> 89336.02 | J71: =J19+J36+J50+J59+J68 -> 6815.385 | K71: =K19+K36+K50+K59+K68 -> 261710 | ... X71: =X19+X36+X50+X59+X68 -> 3.02 | Y71: STATIC | Z71: ROTARY | AA71: piping fab | AB71: piping erec | AC71: PACKAGE/COMPRESSORS | AD71: REFORMER+DUCT & MANIFOOLD | AE71: PRESSURE PARTS | AF71: BOILERS & APH
B72: OHCU CIVIL | D72: =828.76+596.295+25.718+7002.73+677.641+1183.545+165.425+75.8+1078.607+514.559+432.001+277.093 -> 12858.174 | E72: =1000+129+200 -> 1329 | H72: =17167+1643+1079+1041+8212+912+106+61.65+74+51+923+288 -> 31557.65 | I72: 643.399 | J72: 167.527 | L72: =1905+357+1005+942 -> 4209 | U72: 300 | W72: =4873.231+1920.927+912.143+273.058+8224.467 -> 16203.826 | X72: =2613.59 -> 2613.59 | AA72: =1884+20793+6388+2782+3770+1836+2832+2482+312+21+104+2618+1254+70+751.816+453 -> 48350.816 | AB72: =16328.65+6884.414+3574.26+3253.61+2057.06+2986.03+187.266+85.437+376.284+1787.26+1025.834+138.57+453.193+771.441 -> 39909.309
B73: DHDT CIVIL | D73: =836.3+7914.53+1038.27+189.82+1028.22+644.16+627.97+5965*0.15+2057*0.1+3075*0.2+5965*0.15+2067.73*0.1+64.61 -> 15160.853 | E73: 16.12 | H73: =30117+8720+865+31137+1774+4277+6618 -> 83508 | I73: =218+1186+395 -> 1799 | K73: =3131*0.075+1945*0.15+9500*0.23+5971*0.23+2068*0.23 -> 4560.545 | L73: =1574*0.2 -> 314.8 | M73: =3109*0.15 -> 466.35 | R73: 725.4 | AA73: =27778+11578+5485+68+3280+322+424+288 -> 49223 | AB73: =21187+13674+18296 -> 53157
B74: HGU | X74: =1351+68.5 -> 1419.5 | Y74: =1460+274+267 -> 2001 | Z74: =37.57+1.42+76.5 -> 115.49 | AA74: =74078+42393.5+3857+14822 -> 135150.5 | AB74: =109450+6644+26604 -> 142698 | AC74: =79+27.3 -> 106.3 | AD74: =1109+146.42+4.2+176 -> 1435.62 | AE74: 1275 ID | AF74: 254.4
B75: NHT ISOM CIVIL | D75: 1060.71 | E75: 676 | H75: 4394
D76: =SUM(D72:D75) -> 29079.737 | E76: =SUM(E72:E75) -> 2021.12 | F76: =SUM(F72:F75) -> 0 | G76: =SUM(G72:G75) -> 0 | H76: =SUM(H72:H75) -> 119459.65 | I76: =SUM(I72:I75) -> 2442.399 | J76: =SUM(J72:J75) -> 167.527 | K76: =SUM(K72:K75) -> 4560.545 | ... AD76: =SUM(AD72:AD75) -> 1435.62
D77: =D71+D76 -> 236200.51 | E77: =E71+E76 -> 5607.0691 | H77: =H71+H76 -> 5655060.3 | I77: =I71+I76 -> 91778.419 | J77: =J71+J76 -> 6982.912 | K77: =K71+K76 -> 266270.54 | L77: =L71+L76 -> 8464.972 | M77: =M71+M76 -> 170888.56 | N77: =N71+N76 -> 436073.38 | O77: =O71+O76 -> 0 | ... Y77: =Y71+Y76 -> #VALUE!
D78: =D69/8 -> 6739.6474 | E78: =E69/8 -> 206.95124 | H78: =H69/8 -> 231421.92 | N78: =N69/8 -> 13953.419 | O78: =O69/8 -> 0 | P78: =P69/8 -> 561.95875 | Q78: =Q69/8 -> 1635.4964 | R78: =R69/8 -> 1287.6092 | S78: =S69/8 -> 2807.1278 | T78: =T69/8 -> 1.9575 | U78: =U69/8 -> 6214.5825 | ... Y78: =Y69/8 -> 732.1875 | AA78: =AA74/1.5 -> 90100.333 | AB78: =AB74/1.5 -> 95132
AA79: =AA78/15 -> 6006.6889 | AB79: =AB78/15 -> 6342.1333

Sheet WEBSITE
A1: 1 | B1: Specialized in national highways, bridges, industrial projects, and oil & gas infrastructure. Over ₹300 Cr in active order book with a fleet of 200+ equipment units.
A2: 2 | B2: Building India's Infrastructure Since 2001.
A3: 3 | B3: Broadway Links Private Limited (BLPL) is a premier infrastructure development company headquartered in Begusarai, Bihar. With a net worth of ₹170 Crores and a robust asset base of ₹275 Crores, we execute large-scale projects in Highways, Irrigation, and Industrial Oil & Gas sectors.
A4: 4 | B4: ISO 9001: 2015, ISO 45001: 2018, ISO 14001: 2015 COMPLIANT COMPANY (DON’T USE LOGOS)
B5: Our Strength
B6: Group Ecosystem
B7: A diversified conglomerate with a 35-year legacy in Infrastructure, Steel, Mining, Energy and Real Estate
B8: New Way Homes Pvt Ltd Real Estate, Ethanol Productdion (Greater Noida West, Dehradun & Barauni)
B9: Consistent Growth Track Record
B10: With an average annual turnover of ₹221.5 Crores and a strong balance sheet, BLPL demonstrates financial stability and execution capability for large-scale infrastructure projects.
B11: REPLACE TURNOVER GRAPH FROM 2019-20 -2023-24 WITH 2020-21 TO 2024-25 ATTACHED IN FINANCIAL SHEET
B12: 18.51L+ m³ Annual Earthwork Capacity Massive Fleet Deployment
B13: 54k+ m³ Annual Concrete Capacity High-Speed Pavers
B14: ₹1233.7 Cr Current Order Book Strong Pipeline
B15: Our History
A16: YEAR | B16: Milestones of Excellence
A17: 2001 | B17: Company Founded &
A18: 2007 | B18: Stone Mining Operations Sheikhpura Bihar
A19: 2009 | B19: OIL & GAS ENTRY
A20: 2011 | B20: Real Estate ENTRY NWHPL 10Acre GH
A21: 2013 | B21: PWD Contracts ENTRY
A22: 2015 | B22: Stone Mining Operations Palamu Jharkhand
A23: 2017 | B23: 500+ Cr. Order Book
A24: 2018 | B24: Major Heavy Line Fleet Expansion
A25: 2019 | B25: Road Maintenance Entry OPRMC2 Bihar
A26: 2021 | B26: 1000+ Cr. Order Book
A27: 2023 | B27: O&G Mechanical Works ENTRY
A28: 2024 | B28: Ethanol Production
A29: 2025 | B29: ISO 9001: 2015, ISO 45001: 2018, ISO 14001: 2015 COMPLIANT COMPANY (DON’T USE LOGOS)

Sheet HSE
A1: IOCL BARAUNI | B1: 2021 | C1: 2022 | D1: 2023 | E1: 2024 | F1: 2025
A2: DHDT | B2: =SUM([198]DHDT!F4:F7) -> 51630 | C2: =SUM([198]DHDT!F8:F19) -> 289264 | D2: =SUM([198]DHDT!F20:F31) -> 364002 | E2: =SUM([198]DHDT!F32:F33)*6 -> 262692 | F2: =75*26*10*8 -> 156000
A3: OHCU | B3: =SUM('[198]OHCU '!E12) -> 159120 | C3: ='[198]OHCU '!E31 -> 443960 | D3: ='[198]OHCU '!K15 -> 539400 | E3: =45000*12 -> 540000 | F3: =80*26*10*10 -> 208000
A4: EPCM-23 | B4: ='[198]EPCM-23'!E9 -> 45640 | C4: ='[198]EPCM-23'!E25 -> 111128 | D4: ='[198]EPCM-23'!K15 -> 112688 | E4: =10000*12 -> 120000 | F4: =8000*12 -> 96000
A5: HGU-N2 | D5: =[198]Sheet7!B7+[198]Sheet7!C7 -> 276100 | E5: =1171070-276100 -> 894970 | F5: =1727390-E5-D5 -> 556320
B6: =SUM(B2:B5) -> 256390 | C6: =SUM(C2:C5) -> 844352 | D6: =SUM(D2:D5) -> 1292190 | E6: =SUM(E2:E5) -> 1817662 | F6: =SUM(F2:F5) -> 1016320
A7: Total LTA Free Million Manhour | B7: =B6/10^6 -> 0.25639 | C7: =C6/10^6 -> 0.844352 | D7: =D6/10^6 -> 1.29219 | E7: =E6/10^6 -> 1.817662 | F7: =F6/10^6 -> 1.01632
A8: Cumulative LTA Free Million Manhour | B8: =B7 -> 0.25639 | C8: =C7+B8 -> 1.100742 | D8: =D7+C8 -> 2.392932 | E8: =E7+D8 -> 4.210594 | F8: =F7+E8 -> 5.226914
A9: Total Number of Recordables (A + B + C + D)
A10: A. Number of lost workday cases.
A11: B. Number of restricted workday cases.
A12: Without lost workdays.
A13: C. Number of other recordables.
A14: D. Number of fatalities.
A16: Lost Workday Rate (See 1 below)
A17: Recordable Case Rate (See 2 below)
A19: 1. Lost Workday Rate should be calculated for each year using the following formula:
A20: # of Lost Workday Cases (A) X 200,000
A21: # of Hours Worked Annually**
A23: 2. Recordable Rate should be calculated for each year using the following formula:
... A28: # OSHA reference for Air Products internal use. Contractor to complete above table in full
